[
  {
    "date": "2014-04-29T00:00:00",
    "symbol": "AGR",
    "priceHigh": 7.4,
    "priceLow": 6.9,
    "priceOpen": 7.2,
    "priceAverage": 7.1,
    "priceClose": 7.1,
    "priceBasic": 7.3,
    "totalVolume": 935360.0,
    "dealVolume": 935360.0,
    "putthroughVolume": 0.0,
    "totalValue": 6641056000.0,
    "putthroughValue": 0.0,
    "buyForeignQuantity": 10000.0,
    "buyForeignValue": 73000000.0,
    "sellForeignQuantity": 0.0,
    "sellForeignValue": 0.0,
    "buyCount": 628.0,
    "buyQuantity": 2137040.0,
    "sellCount": 414.0,
    "sellQuantity": 2259240.0,
    "adjRatio": 1.2670195506180124,
    "currentForeignRoom": 103350501.0,
    "propTradingNetDealValue": null,
    "propTradingNetPTValue": null,
    "propTradingNetValue": null,
    "unit": 1000.0
  },
  {
    "date": "2014-04-28T00:00:00",
    "symbol": "AGR",
    "priceHigh": 7.9,
    "priceLow": 7.3,
    "priceOpen": 7.9,
    "priceAverage": 7.3,
    "priceClose": 7.3,
    "priceBasic": 7.8,
    "totalVolume": 722470.0,
    "dealVolume": 722470.0,
    "putthroughVolume": 0.0,
    "totalValue": 5274031000.0,
    "putthroughValue": 0.0,
    "buyForeignQuantity": 0.0,
    "buyForeignValue": 0.0,
    "sellForeignQuantity": 8300.0,
    "sellForeignValue": 63910000.0,
    "buyCount": 371.0,
    "buyQuantity": 1223410.0,
    "sellCount": 325.0,
    "sellQuantity": 1887160.0,
    "adjRatio": 1.2670195506180124,
    "currentForeignRoom": 103360501.0,
    "propTradingNetDealValue": null,
    "propTradingNetPTValue": null,
    "propTradingNetValue": null,
    "unit": 1000.0
  },
  {
    "date": "2014-04-25T00:00:00",
    "symbol": "AGR",
    "priceHigh": 8.0,
    "priceLow": 7.6,
    "priceOpen": 7.8,
    "priceAverage": 7.8,
    "priceClose": 7.8,
    "priceBasic": 7.7,
    "totalVolume": 1240770.0,
    "dealVolume": 1240770.0,
    "putthroughVolume": 0.0,
    "totalValue": 9678006000.0,
    "putthroughValue": 0.0,
    "buyForeignQuantity": 0.0,
    "buyForeignValue": 0.0,
    "sellForeignQuantity": 39700.0,
    "sellForeignValue": 309310000.0,
    "buyCount": 565.0,
    "buyQuantity": 2535080.0,
    "sellCount": 432.0,
    "sellQuantity": 2405020.0,
    "adjRatio": 1.2670195506180124,
    "currentForeignRoom": 103360501.0,
    "propTradingNetDealValue": null,
    "propTradingNetPTValue": null,
    "propTradingNetValue": null,
    "unit": 1000.0
  },
  {
    "date": "2014-04-24T00:00:00",
    "symbol": "AGR",
    "priceHigh": 8.0,
    "priceLow": 7.7,
    "priceOpen": 7.8,
    "priceAverage": 7.7,
    "priceClose": 7.7,
    "priceBasic": 7.8,
    "totalVolume": 494220.0,
    "dealVolume": 494220.0,
    "putthroughVolume": 0.0,
    "totalValue": 3805494000.0,
    "putthroughValue": 0.0,
    "buyForeignQuantity": 0.0,
    "buyForeignValue": 0.0,
    "sellForeignQuantity": 0.0,
    "sellForeignValue": 0.0,
    "buyCount": 399.0,
    "buyQuantity": 1305700.0,
    "sellCount": 340.0,
    "sellQuantity": 1659020.0,
    "adjRatio": 1.2670195506180124,
    "currentForeignRoom": 103360501.0,
    "propTradingNetDealValue": null,
    "propTradingNetPTValue": null,
    "propTradingNetValue": null,
    "unit": 1000.0
  },
  {
    "date": "2014-04-23T00:00:00",
    "symbol": "AGR",
    "priceHigh": 8.3,
    "priceLow": 7.8,
    "priceOpen": 8.3,
    "priceAverage": 7.8,
    "priceClose": 7.8,
    "priceBasic": 8.3,
    "totalVolume": 1133020.0,
    "dealVolume": 1133020.0,
    "putthroughVolume": 0.0,
    "totalValue": 8837556000.0,
    "putthroughValue": 0.0,
    "buyForeignQuantity": 0.0,
    "buyForeignValue": 0.0,
    "sellForeignQuantity": 0.0,
    "sellForeignValue": 0.0,
    "buyCount": 543.0,
    "buyQuantity": 1841210.0,
    "sellCount": 566.0,
    "sellQuantity": 3206800.0,
    "adjRatio": 1.2670195506180124,
    "currentForeignRoom": 103360501.0,
    "propTradingNetDealValue": null,
    "propTradingNetPTValue": null,
    "propTradingNetValue": null,
    "unit": 1000.0
  },
  {
    "date": "2014-04-22T00:00:00",
    "symbol": "AGR",
    "priceHigh": 8.3,
    "priceLow": 7.5,
    "priceOpen": 8.0,
    "priceAverage": 8.3,
    "priceClose": 8.3,
    "priceBasic": 7.9,
    "totalVolume": 1490410.0,
    "dealVolume": 1490410.0,
    "putthroughVolume": 0.0,
    "totalValue": 12370403000.0,
    "putthroughValue": 0.0,
    "buyForeignQuantity": 30000.0,
    "buyForeignValue": 235000000.0,
    "sellForeignQuantity": 0.0,
    "sellForeignValue": 0.0,
    "buyCount": 743.0,
    "buyQuantity": 3224920.0,
    "sellCount": 532.0,
    "sellQuantity": 3118910.0,
    "adjRatio": 1.2670195506180124,
    "currentForeignRoom": 103360501.0,
    "propTradingNetDealValue": null,
    "propTradingNetPTValue": null,
    "propTradingNetValue": null,
    "unit": 1000.0
  },
  {
    "date": "2014-04-21T00:00:00",
    "symbol": "AGR",
    "priceHigh": 8.4,
    "priceLow": 7.9,
    "priceOpen": 8.3,
    "priceAverage": 7.9,
    "priceClose": 7.9,
    "priceBasic": 8.3,
    "totalVolume": 869420.0,
    "dealVolume": 869420.0,
    "putthroughVolume": 0.0,
    "totalValue": 6868418000.0,
    "putthroughValue": 0.0,
    "buyForeignQuantity": 8500.0,
    "buyForeignValue": 67150000.0,
    "sellForeignQuantity": 0.0,
    "sellForeignValue": 0.0,
    "buyCount": 413.0,
    "buyQuantity": 1787420.0,
    "sellCount": 473.0,
    "sellQuantity": 2237520.0,
    "adjRatio": 1.2670195506180124,
    "currentForeignRoom": 103360501.0,
    "propTradingNetDealValue": null,
    "propTradingNetPTValue": null,
    "propTradingNetValue": null,
    "unit": 1000.0
  },
  {
    "date": "2014-04-18T00:00:00",
    "symbol": "AGR",
    "priceHigh": 8.6,
    "priceLow": 8.2,
    "priceOpen": 8.6,
    "priceAverage": 8.3,
    "priceClose": 8.3,
    "priceBasic": 8.5,
    "totalVolume": 1808060.0,
    "dealVolume": 1808060.0,
    "putthroughVolume": 0.0,
    "totalValue": 15006898000.0,
    "putthroughValue": 0.0,
    "buyForeignQuantity": 0.0,
    "buyForeignValue": 0.0,
    "sellForeignQuantity": 0.0,
    "sellForeignValue": 0.0,
    "buyCount": 612.0,
    "buyQuantity": 2865880.0,
    "sellCount": 730.0,
    "sellQuantity": 4017740.0,
    "adjRatio": 1.2670195506180124,
    "currentForeignRoom": 103369001.0,
    "propTradingNetDealValue": null,
    "propTradingNetPTValue": null,
    "propTradingNetValue": null,
    "unit": 1000.0
  },
  {
    "date": "2014-04-17T00:00:00",
    "symbol": "AGR",
    "priceHigh": 8.5,
    "priceLow": 8.1,
    "priceOpen": 8.4,
    "priceAverage": 8.5,
    "priceClose": 8.5,
    "priceBasic": 8.0,
    "totalVolume": 1711600.0,
    "dealVolume": 1711600.0,
    "putthroughVolume": 0.0,
    "totalValue": 14548600000.0,
    "putthroughValue": 0.0,
    "buyForeignQuantity": 10450.0,
    "buyForeignValue": 87755000.0,
    "sellForeignQuantity": 0.0,
    "sellForeignValue": 0.0,
    "buyCount": 886.0,
    "buyQuantity": 5801290.0,
    "sellCount": 380.0,
    "sellQuantity": 2402650.0,
    "adjRatio": 1.2670195506180124,
    "currentForeignRoom": 103344001.0,
    "propTradingNetDealValue": null,
    "propTradingNetPTValue": null,
    "propTradingNetValue": null,
    "unit": 1000.0
  },
  {
    "date": "2014-04-16T00:00:00",
    "symbol": "AGR",
    "priceHigh": 8.6,
    "priceLow": 8.0,
    "priceOpen": 8.5,
    "priceAverage": 8.0,
    "priceClose": 8.0,
    "priceBasic": 8.6,
    "totalVolume": 1655180.0,
    "dealVolume": 1655180.0,
    "putthroughVolume": 0.0,
    "totalValue": 13241440000.0,
    "putthroughValue": 0.0,
    "buyForeignQuantity": 0.0,
    "buyForeignValue": 0.0,
    "sellForeignQuantity": 30000.0,
    "sellForeignValue": 254000000.0,
    "buyCount": 584.0,
    "buyQuantity": 2303960.0,
    "sellCount": 693.0,
    "sellQuantity": 3448730.0,
    "adjRatio": 1.2670195506180124,
    "currentForeignRoom": 103354451.0,
    "propTradingNetDealValue": null,
    "propTradingNetPTValue": null,
    "propTradingNetValue": null,
    "unit": 1000.0
  },
  {
    "date": "2014-04-15T00:00:00",
    "symbol": "AGR",
    "priceHigh": 9.1,
    "priceLow": 8.6,
    "priceOpen": 9.0,
    "priceAverage": 8.6,
    "priceClose": 8.6,
    "priceBasic": 8.8,
    "totalVolume": 2089890.0,
    "dealVolume": 2089890.0,
    "putthroughVolume": 0.0,
    "totalValue": 17973054000.0,
    "putthroughValue": 0.0,
    "buyForeignQuantity": 0.0,
    "buyForeignValue": 0.0,
    "sellForeignQuantity": 0.0,
    "sellForeignValue": 0.0,
    "buyCount": 627.0,
    "buyQuantity": 3548390.0,
    "sellCount": 1334.0,
    "sellQuantity": 6105560.0,
    "adjRatio": 1.2670195506180124,
    "currentForeignRoom": 103319451.0,
    "propTradingNetDealValue": null,
    "propTradingNetPTValue": null,
    "propTradingNetValue": null,
    "unit": 1000.0
  },
  {
    "date": "2014-04-14T00:00:00",
    "symbol": "AGR",
    "priceHigh": 9.0,
    "priceLow": 8.7,
    "priceOpen": 8.7,
    "priceAverage": 8.8,
    "priceClose": 8.8,
    "priceBasic": 8.5,
    "totalVolume": 2625060.0,
    "dealVolume": 2625060.0,
    "putthroughVolume": 0.0,
    "totalValue": 23100528000.0,
    "putthroughValue": 0.0,
    "buyForeignQuantity": 0.0,
    "buyForeignValue": 0.0,
    "sellForeignQuantity": 25000.0,
    "sellForeignValue": 219000000.0,
    "buyCount": 716.0,
    "buyQuantity": 5222760.0,
    "sellCount": 1081.0,
    "sellQuantity": 5389570.0,
    "adjRatio": 1.2670195506180124,
    "currentForeignRoom": 103319451.0,
    "propTradingNetDealValue": null,
    "propTradingNetPTValue": null,
    "propTradingNetValue": null,
    "unit": 1000.0
  },
  {
    "date": "2014-04-11T00:00:00",
    "symbol": "AGR",
    "priceHigh": 8.7,
    "priceLow": 8.3,
    "priceOpen": 8.6,
    "priceAverage": 8.5,
    "priceClose": 8.5,
    "priceBasic": 8.6,
    "totalVolume": 1055350.0,
    "dealVolume": 1055350.0,
    "putthroughVolume": 0.0,
    "totalValue": 8970475000.0,
    "putthroughValue": 0.0,
    "buyForeignQuantity": 0.0,
    "buyForeignValue": 266400000.0,
    "sellForeignQuantity": 35000.0,
    "sellForeignValue": 299500000.0,
    "buyCount": 646.0,
    "buyQuantity": 3533750.0,
    "sellCount": 577.0,
    "sellQuantity": 2846110.0,
    "adjRatio": 1.2670195506180124,
    "currentForeignRoom": 103319451.0,
    "propTradingNetDealValue": null,
    "propTradingNetPTValue": null,
    "propTradingNetValue": null,
    "unit": 1000.0
  },
  {
    "date": "2014-04-10T00:00:00",
    "symbol": "AGR",
    "priceHigh": 8.9,
    "priceLow": 8.5,
    "priceOpen": 8.8,
    "priceAverage": 8.6,
    "priceClose": 8.6,
    "priceBasic": 8.6,
    "totalVolume": 881390.0,
    "dealVolume": 881390.0,
    "putthroughVolume": 0.0,
    "totalValue": 7579954000.0,
    "putthroughValue": 0.0,
    "buyForeignQuantity": 0.0,
    "buyForeignValue": 0.0,
    "sellForeignQuantity": 0.0,
    "sellForeignValue": 0.0,
    "buyCount": 383.0,
    "buyQuantity": 1797640.0,
    "sellCount": 762.0,
    "sellQuantity": 3268770.0,
    "adjRatio": 1.2670195506180124,
    "currentForeignRoom": 103312451.0,
    "propTradingNetDealValue": null,
    "propTradingNetPTValue": null,
    "propTradingNetValue": null,
    "unit": 1000.0
  },
  {
    "date": "2014-04-08T00:00:00",
    "symbol": "AGR",
    "priceHigh": 9.0,
    "priceLow": 8.6,
    "priceOpen": 8.8,
    "priceAverage": 8.6,
    "priceClose": 8.6,
    "priceBasic": 8.7,
    "totalVolume": 1032990.0,
    "dealVolume": 1032990.0,
    "putthroughVolume": 0.0,
    "totalValue": 8883714000.0,
    "putthroughValue": 0.0,
    "buyForeignQuantity": 0.0,
    "buyForeignValue": 0.0,
    "sellForeignQuantity": 0.0,
    "sellForeignValue": 0.0,
    "buyCount": 473.0,
    "buyQuantity": 2190670.0,
    "sellCount": 873.0,
    "sellQuantity": 4216030.0,
    "adjRatio": 1.2670195506180124,
    "currentForeignRoom": 103312451.0,
    "propTradingNetDealValue": null,
    "propTradingNetPTValue": null,
    "propTradingNetValue": null,
    "unit": 1000.0
  },
  {
    "date": "2014-04-07T00:00:00",
    "symbol": "AGR",
    "priceHigh": 8.8,
    "priceLow": 8.1,
    "priceOpen": 8.2,
    "priceAverage": 8.7,
    "priceClose": 8.7,
    "priceBasic": 8.3,
    "totalVolume": 1759030.0,
    "dealVolume": 1759030.0,
    "putthroughVolume": 0.0,
    "totalValue": 15303561000.0,
    "putthroughValue": 0.0,
    "buyForeignQuantity": 61100.0,
    "buyForeignValue": 514520000.0,
    "sellForeignQuantity": 0.0,
    "sellForeignValue": 0.0,
    "buyCount": 518.0,
    "buyQuantity": 3293260.0,
    "sellCount": 701.0,
    "sellQuantity": 3052890.0,
    "adjRatio": 1.2670195506180124,
    "currentForeignRoom": 103312451.0,
    "propTradingNetDealValue": null,
    "propTradingNetPTValue": null,
    "propTradingNetValue": null,
    "unit": 1000.0
  },
  {
    "date": "2014-04-04T00:00:00",
    "symbol": "AGR",
    "priceHigh": 8.6,
    "priceLow": 8.1,
    "priceOpen": 8.5,
    "priceAverage": 8.3,
    "priceClose": 8.3,
    "priceBasic": 8.4,
    "totalVolume": 1052010.0,
    "dealVolume": 1052010.0,
    "putthroughVolume": 0.0,
    "totalValue": 8731683000.0,
    "putthroughValue": 0.0,
    "buyForeignQuantity": 0.0,
    "buyForeignValue": 0.0,
    "sellForeignQuantity": 38000.0,
    "sellForeignValue": 311642000.0,
    "buyCount": 474.0,
    "buyQuantity": 2365540.0,
    "sellCount": 590.0,
    "sellQuantity": 3047630.0,
    "adjRatio": 1.2670195506180124,
    "currentForeignRoom": 103373551.0,
    "propTradingNetDealValue": null,
    "propTradingNetPTValue": null,
    "propTradingNetValue": null,
    "unit": 1000.0
  },
  {
    "date": "2014-04-03T00:00:00",
    "symbol": "AGR",
    "priceHigh": 8.4,
    "priceLow": 8.0,
    "priceOpen": 8.1,
    "priceAverage": 8.4,
    "priceClose": 8.4,
    "priceBasic": 7.9,
    "totalVolume": 1277910.0,
    "dealVolume": 1277910.0,
    "putthroughVolume": 0.0,
    "totalValue": 10734444000.0,
    "putthroughValue": 0.0,
    "buyForeignQuantity": 0.0,
    "buyForeignValue": 0.0,
    "sellForeignQuantity": 0.0,
    "sellForeignValue": 0.0,
    "buyCount": 662.0,
    "buyQuantity": 3002970.0,
    "sellCount": 393.0,
    "sellQuantity": 2151760.0,
    "adjRatio": 1.2670195506180124,
    "currentForeignRoom": 103373551.0,
    "propTradingNetDealValue": null,
    "propTradingNetPTValue": null,
    "propTradingNetValue": null,
    "unit": 1000.0
  },
  {
    "date": "2014-04-02T00:00:00",
    "symbol": "AGR",
    "priceHigh": 8.3,
    "priceLow": 7.8,
    "priceOpen": 8.2,
    "priceAverage": 7.9,
    "priceClose": 7.9,
    "priceBasic": 8.3,
    "totalVolume": 2000780.0,
    "dealVolume": 2000780.0,
    "putthroughVolume": 0.0,
    "totalValue": 15806162000.0,
    "putthroughValue": 0.0,
    "buyForeignQuantity": 0.0,
    "buyForeignValue": 0.0,
    "sellForeignQuantity": 0.0,
    "sellForeignValue": 0.0,
    "buyCount": 705.0,
    "buyQuantity": 2806290.0,
    "sellCount": 748.0,
    "sellQuantity": 3977860.0,
    "adjRatio": 1.2670195506180124,
    "currentForeignRoom": 103373551.0,
    "propTradingNetDealValue": null,
    "propTradingNetPTValue": null,
    "propTradingNetValue": null,
    "unit": 1000.0
  },
  {
    "date": "2014-04-01T00:00:00",
    "symbol": "AGR",
    "priceHigh": 8.7,
    "priceLow": 8.2,
    "priceOpen": 8.7,
    "priceAverage": 8.3,
    "priceClose": 8.3,
    "priceBasic": 8.8,
    "totalVolume": 1738750.0,
    "dealVolume": 1738750.0,
    "putthroughVolume": 0.0,
    "totalValue": 14431625000.0,
    "putthroughValue": 0.0,
    "buyForeignQuantity": 0.0,
    "buyForeignValue": 0.0,
    "sellForeignQuantity": 0.0,
    "sellForeignValue": 0.0,
    "buyCount": 737.0,
    "buyQuantity": 2883010.0,
    "sellCount": 668.0,
    "sellQuantity": 3768760.0,
    "adjRatio": 1.2670195506180124,
    "currentForeignRoom": 103373551.0,
    "propTradingNetDealValue": null,
    "propTradingNetPTValue": null,
    "propTradingNetValue": null,
    "unit": 1000.0
  }
]