[
  {
    "date": "2020-08-31T00:00:00",
    "symbol": "TVB",
    "priceHigh": 7.7,
    "priceLow": 7.45,
    "priceOpen": 7.7,
    "priceAverage": 7.587168758716876,
    "priceClose": 7.55,
    "priceBasic": 7.71,
    "totalVolume": 215100.0,
    "dealVolume": 215100.0,
    "putthroughVolume": 0.0,
    "totalValue": 1632000000.0,
    "putthroughValue": 0.0,
    "buyForeignQuantity": 3410.0,
    "buyForeignValue": 25860000.0,
    "sellForeignQuantity": 2630.0,
    "sellForeignValue": 19970000.0,
    "buyCount": 213.0,
    "buyQuantity": 363530.0,
    "sellCount": 162.0,
    "sellQuantity": 449500.0,
    "adjRatio": 1.5990314191472081,
    "currentForeignRoom": 25104643.0,
    "propTradingNetDealValue": null,
    "propTradingNetPTValue": null,
    "propTradingNetValue": null,
    "unit": 1000.0
  },
  {
    "date": "2020-08-28T00:00:00",
    "symbol": "TVB",
    "priceHigh": 7.8,
    "priceLow": 7.71,
    "priceOpen": 7.8,
    "priceAverage": 7.765370299063021,
    "priceClose": 7.71,
    "priceBasic": 7.74,
    "totalVolume": 155820.0,
    "dealVolume": 155820.0,
    "putthroughVolume": 0.0,
    "totalValue": 1210000000.0,
    "putthroughValue": 0.0,
    "buyForeignQuantity": 7960.0,
    "buyForeignValue": 61940000.0,
    "sellForeignQuantity": 0.0,
    "sellForeignValue": 0.0,
    "buyCount": 146.0,
    "buyQuantity": 229520.0,
    "sellCount": 161.0,
    "sellQuantity": 429560.0,
    "adjRatio": 1.5990314191472081,
    "currentForeignRoom": 25107053.0,
    "propTradingNetDealValue": null,
    "propTradingNetPTValue": null,
    "propTradingNetValue": null,
    "unit": 1000.0
  },
  {
    "date": "2020-08-27T00:00:00",
    "symbol": "TVB",
    "priceHigh": 7.8,
    "priceLow": 7.6,
    "priceOpen": 7.7,
    "priceAverage": 7.703997357119261,
    "priceClose": 7.74,
    "priceBasic": 7.56,
    "totalVolume": 151350.0,
    "dealVolume": 151350.0,
    "putthroughVolume": 0.0,
    "totalValue": 1166000000.0,
    "putthroughValue": 0.0,
    "buyForeignQuantity": 9310.0,
    "buyForeignValue": 71620000.0,
    "sellForeignQuantity": 0.0,
    "sellForeignValue": 0.0,
    "buyCount": 186.0,
    "buyQuantity": 311850.0,
    "sellCount": 168.0,
    "sellQuantity": 447850.0,
    "adjRatio": 1.5990314191472081,
    "currentForeignRoom": 25115003.0,
    "propTradingNetDealValue": null,
    "propTradingNetPTValue": null,
    "propTradingNetValue": null,
    "unit": 1000.0
  },
  {
    "date": "2020-08-26T00:00:00",
    "symbol": "TVB",
    "priceHigh": 7.56,
    "priceLow": 7.4,
    "priceOpen": 7.52,
    "priceAverage": 7.522212040320332,
    "priceClose": 7.56,
    "priceBasic": 7.46,
    "totalVolume": 250990.0,
    "dealVolume": 250990.0,
    "putthroughVolume": 0.0,
    "totalValue": 1888000000.0,
    "putthroughValue": 0.0,
    "buyForeignQuantity": 25850.0,
    "buyForeignValue": 194530000.0,
    "sellForeignQuantity": 1000.0,
    "sellForeignValue": 7540000.0,
    "buyCount": 217.0,
    "buyQuantity": 496550.0,
    "sellCount": 178.0,
    "sellQuantity": 465630.0,
    "adjRatio": 1.5990314191472081,
    "currentForeignRoom": 25124313.0,
    "propTradingNetDealValue": null,
    "propTradingNetPTValue": null,
    "propTradingNetValue": null,
    "unit": 1000.0
  },
  {
    "date": "2020-08-25T00:00:00",
    "symbol": "TVB",
    "priceHigh": 7.5,
    "priceLow": 7.39,
    "priceOpen": 7.48,
    "priceAverage": 7.444311771729732,
    "priceClose": 7.46,
    "priceBasic": 7.44,
    "totalVolume": 242870.0,
    "dealVolume": 242870.0,
    "putthroughVolume": 0.0,
    "totalValue": 1808000000.0,
    "putthroughValue": 0.0,
    "buyForeignQuantity": 11190.0,
    "buyForeignValue": 83520000.0,
    "sellForeignQuantity": 10.0,
    "sellForeignValue": 70000.0,
    "buyCount": 213.0,
    "buyQuantity": 468890.0,
    "sellCount": 160.0,
    "sellQuantity": 561810.0,
    "adjRatio": 1.5990314191472081,
    "currentForeignRoom": 25150163.0,
    "propTradingNetDealValue": null,
    "propTradingNetPTValue": null,
    "propTradingNetValue": null,
    "unit": 1000.0
  },
  {
    "date": "2020-08-24T00:00:00",
    "symbol": "TVB",
    "priceHigh": 7.45,
    "priceLow": 7.27,
    "priceOpen": 7.27,
    "priceAverage": 7.3897568920793875,
    "priceClose": 7.44,
    "priceBasic": 7.3,
    "totalVolume": 165770.0,
    "dealVolume": 165770.0,
    "putthroughVolume": 0.0,
    "totalValue": 1225000000.0,
    "putthroughValue": 0.0,
    "buyForeignQuantity": 22790.0,
    "buyForeignValue": 168620000.0,
    "sellForeignQuantity": 0.0,
    "sellForeignValue": 0.0,
    "buyCount": 258.0,
    "buyQuantity": 478500.0,
    "sellCount": 148.0,
    "sellQuantity": 416900.0,
    "adjRatio": 1.5990314191472081,
    "currentForeignRoom": 23449091.0,
    "propTradingNetDealValue": null,
    "propTradingNetPTValue": null,
    "propTradingNetValue": null,
    "unit": 1000.0
  },
  {
    "date": "2020-08-21T00:00:00",
    "symbol": "TVB",
    "priceHigh": 7.32,
    "priceLow": 7.2,
    "priceOpen": 7.22,
    "priceAverage": 7.269548904238083,
    "priceClose": 7.3,
    "priceBasic": 7.22,
    "totalVolume": 234540.0,
    "dealVolume": 234540.0,
    "putthroughVolume": 0.0,
    "totalValue": 1705000000.0,
    "putthroughValue": 0.0,
    "buyForeignQuantity": 6030.0,
    "buyForeignValue": 43970000.0,
    "sellForeignQuantity": 0.0,
    "sellForeignValue": 0.0,
    "buyCount": 200.0,
    "buyQuantity": 459240.0,
    "sellCount": 153.0,
    "sellQuantity": 513990.0,
    "adjRatio": 1.5990314191472081,
    "currentForeignRoom": 23471881.0,
    "propTradingNetDealValue": null,
    "propTradingNetPTValue": null,
    "propTradingNetValue": null,
    "unit": 1000.0
  },
  {
    "date": "2020-08-20T00:00:00",
    "symbol": "TVB",
    "priceHigh": 7.4,
    "priceLow": 7.22,
    "priceOpen": 7.23,
    "priceAverage": 7.292929292929293,
    "priceClose": 7.22,
    "priceBasic": 7.23,
    "totalVolume": 346500.0,
    "dealVolume": 346500.0,
    "putthroughVolume": 0.0,
    "totalValue": 2527000000.0,
    "putthroughValue": 0.0,
    "buyForeignQuantity": 990.0,
    "buyForeignValue": 7210000.0,
    "sellForeignQuantity": 0.0,
    "sellForeignValue": 0.0,
    "buyCount": 199.0,
    "buyQuantity": 547670.0,
    "sellCount": 176.0,
    "sellQuantity": 634430.0,
    "adjRatio": 1.5990314191472081,
    "currentForeignRoom": 23477911.0,
    "propTradingNetDealValue": null,
    "propTradingNetPTValue": null,
    "propTradingNetValue": null,
    "unit": 1000.0
  },
  {
    "date": "2020-08-19T00:00:00",
    "symbol": "TVB",
    "priceHigh": 7.29,
    "priceLow": 7.21,
    "priceOpen": 7.22,
    "priceAverage": 7.267470840394776,
    "priceClose": 7.23,
    "priceBasic": 7.22,
    "totalVolume": 300930.0,
    "dealVolume": 300930.0,
    "putthroughVolume": 0.0,
    "totalValue": 2187000000.0,
    "putthroughValue": 0.0,
    "buyForeignQuantity": 8450.0,
    "buyForeignValue": 61520000.0,
    "sellForeignQuantity": 0.0,
    "sellForeignValue": 0.0,
    "buyCount": 184.0,
    "buyQuantity": 444280.0,
    "sellCount": 178.0,
    "sellQuantity": 774020.0,
    "adjRatio": 1.5990314191472081,
    "currentForeignRoom": 23473291.0,
    "propTradingNetDealValue": null,
    "propTradingNetPTValue": null,
    "propTradingNetValue": null,
    "unit": 1000.0
  },
  {
    "date": "2020-08-18T00:00:00",
    "symbol": "TVB",
    "priceHigh": 7.4,
    "priceLow": 7.16,
    "priceOpen": 7.21,
    "priceAverage": 7.272680663436643,
    "priceClose": 7.22,
    "priceBasic": 7.21,
    "totalVolume": 390090.0,
    "dealVolume": 390090.0,
    "putthroughVolume": 0.0,
    "totalValue": 2837000000.0,
    "putthroughValue": 0.0,
    "buyForeignQuantity": 5880.0,
    "buyForeignValue": 42680000.0,
    "sellForeignQuantity": 0.0,
    "sellForeignValue": 0.0,
    "buyCount": 241.0,
    "buyQuantity": 579980.0,
    "sellCount": 218.0,
    "sellQuantity": 782540.0,
    "adjRatio": 1.5990314191472081,
    "currentForeignRoom": 23481501.0,
    "propTradingNetDealValue": null,
    "propTradingNetPTValue": null,
    "propTradingNetValue": null,
    "unit": 1000.0
  },
  {
    "date": "2020-08-17T00:00:00",
    "symbol": "TVB",
    "priceHigh": 7.3,
    "priceLow": 7.15,
    "priceOpen": 7.2,
    "priceAverage": 7.2131849315068495,
    "priceClose": 7.21,
    "priceBasic": 7.21,
    "totalVolume": 327040.0,
    "dealVolume": 327040.0,
    "putthroughVolume": 0.0,
    "totalValue": 2359000000.0,
    "putthroughValue": 0.0,
    "buyForeignQuantity": 0.0,
    "buyForeignValue": 0.0,
    "sellForeignQuantity": 5610.0,
    "sellForeignValue": 40370000.0,
    "buyCount": 212.0,
    "buyQuantity": 447010.0,
    "sellCount": 222.0,
    "sellQuantity": 680870.0,
    "adjRatio": 1.5990314191472081,
    "currentForeignRoom": 23487381.0,
    "propTradingNetDealValue": null,
    "propTradingNetPTValue": null,
    "propTradingNetValue": null,
    "unit": 1000.0
  },
  {
    "date": "2020-08-14T00:00:00",
    "symbol": "TVB",
    "priceHigh": 7.3,
    "priceLow": 7.15,
    "priceOpen": 7.21,
    "priceAverage": 7.202354232131278,
    "priceClose": 7.21,
    "priceBasic": 7.22,
    "totalVolume": 200490.0,
    "dealVolume": 200490.0,
    "putthroughVolume": 0.0,
    "totalValue": 1444000000.0,
    "putthroughValue": 0.0,
    "buyForeignQuantity": 3390.0,
    "buyForeignValue": 24430000.0,
    "sellForeignQuantity": 240.0,
    "sellForeignValue": 1750000.0,
    "buyCount": 231.0,
    "buyQuantity": 506880.0,
    "sellCount": 189.0,
    "sellQuantity": 487620.0,
    "adjRatio": 1.5990314191472081,
    "currentForeignRoom": 23486361.0,
    "propTradingNetDealValue": null,
    "propTradingNetPTValue": null,
    "propTradingNetValue": null,
    "unit": 1000.0
  },
  {
    "date": "2020-08-13T00:00:00",
    "symbol": "TVB",
    "priceHigh": 7.28,
    "priceLow": 7.0,
    "priceOpen": 7.22,
    "priceAverage": 7.197360280470201,
    "priceClose": 7.22,
    "priceBasic": 7.22,
    "totalVolume": 290940.0,
    "dealVolume": 290940.0,
    "putthroughVolume": 0.0,
    "totalValue": 2094000000.0,
    "putthroughValue": 0.0,
    "buyForeignQuantity": 9880.0,
    "buyForeignValue": 71430000.0,
    "sellForeignQuantity": 0.0,
    "sellForeignValue": 0.0,
    "buyCount": 353.0,
    "buyQuantity": 642230.0,
    "sellCount": 229.0,
    "sellQuantity": 504390.0,
    "adjRatio": 1.5990314191472081,
    "currentForeignRoom": 23477021.0,
    "propTradingNetDealValue": null,
    "propTradingNetPTValue": null,
    "propTradingNetValue": null,
    "unit": 1000.0
  },
  {
    "date": "2020-08-12T00:00:00",
    "symbol": "TVB",
    "priceHigh": 7.3,
    "priceLow": 7.11,
    "priceOpen": 7.11,
    "priceAverage": 7.2377592534638255,
    "priceClose": 7.22,
    "priceBasic": 7.11,
    "totalVolume": 351490.0,
    "dealVolume": 351490.0,
    "putthroughVolume": 0.0,
    "totalValue": 2544000000.0,
    "putthroughValue": 0.0,
    "buyForeignQuantity": 6620.0,
    "buyForeignValue": 48190000.0,
    "sellForeignQuantity": 1020.0,
    "sellForeignValue": 7330000.0,
    "buyCount": 354.0,
    "buyQuantity": 714100.0,
    "sellCount": 268.0,
    "sellQuantity": 635730.0,
    "adjRatio": 1.5990314191472081,
    "currentForeignRoom": 23443111.0,
    "propTradingNetDealValue": null,
    "propTradingNetPTValue": null,
    "propTradingNetValue": null,
    "unit": 1000.0
  },
  {
    "date": "2020-08-11T00:00:00",
    "symbol": "TVB",
    "priceHigh": 7.19,
    "priceLow": 6.91,
    "priceOpen": 6.91,
    "priceAverage": 7.032545153128,
    "priceClose": 7.11,
    "priceBasic": 7.03,
    "totalVolume": 229220.0,
    "dealVolume": 229220.0,
    "putthroughVolume": 0.0,
    "totalValue": 1612000000.0,
    "putthroughValue": 0.0,
    "buyForeignQuantity": 3000.0,
    "buyForeignValue": 21270000.0,
    "sellForeignQuantity": 12730.0,
    "sellForeignValue": 89290000.0,
    "buyCount": 327.0,
    "buyQuantity": 757280.0,
    "sellCount": 172.0,
    "sellQuantity": 475970.0,
    "adjRatio": 1.5990314191472081,
    "currentForeignRoom": 23449301.0,
    "propTradingNetDealValue": null,
    "propTradingNetPTValue": null,
    "propTradingNetValue": null,
    "unit": 1000.0
  },
  {
    "date": "2020-08-10T00:00:00",
    "symbol": "TVB",
    "priceHigh": 7.25,
    "priceLow": 7.02,
    "priceOpen": 7.25,
    "priceAverage": 7.100423177083333,
    "priceClose": 7.03,
    "priceBasic": 7.03,
    "totalVolume": 245760.0,
    "dealVolume": 245760.0,
    "putthroughVolume": 0.0,
    "totalValue": 1745000000.0,
    "putthroughValue": 0.0,
    "buyForeignQuantity": 440.0,
    "buyForeignValue": 3130000.0,
    "sellForeignQuantity": 43790.0,
    "sellForeignValue": 308490000.0,
    "buyCount": 343.0,
    "buyQuantity": 694410.0,
    "sellCount": 194.0,
    "sellQuantity": 810750.0,
    "adjRatio": 1.5990314191472081,
    "currentForeignRoom": 23445931.0,
    "propTradingNetDealValue": null,
    "propTradingNetPTValue": null,
    "propTradingNetValue": null,
    "unit": 1000.0
  },
  {
    "date": "2020-08-07T00:00:00",
    "symbol": "TVB",
    "priceHigh": 7.25,
    "priceLow": 6.9,
    "priceOpen": 6.9,
    "priceAverage": 7.0990260654168775,
    "priceClose": 7.03,
    "priceBasic": 7.15,
    "totalVolume": 177630.0,
    "dealVolume": 177630.0,
    "putthroughVolume": 0.0,
    "totalValue": 1261000000.0,
    "putthroughValue": 0.0,
    "buyForeignQuantity": 1470.0,
    "buyForeignValue": 10420000.0,
    "sellForeignQuantity": 430.0,
    "sellForeignValue": 3050000.0,
    "buyCount": 262.0,
    "buyQuantity": 480800.0,
    "sellCount": 217.0,
    "sellQuantity": 512870.0,
    "adjRatio": 1.5990314191472081,
    "currentForeignRoom": 23436371.0,
    "propTradingNetDealValue": null,
    "propTradingNetPTValue": null,
    "propTradingNetValue": null,
    "unit": 1000.0
  },
  {
    "date": "2020-08-06T00:00:00",
    "symbol": "TVB",
    "priceHigh": 7.2,
    "priceLow": 7.0,
    "priceOpen": 7.2,
    "priceAverage": 7.074104140090456,
    "priceClose": 7.15,
    "priceBasic": 7.2,
    "totalVolume": 172460.0,
    "dealVolume": 172460.0,
    "putthroughVolume": 0.0,
    "totalValue": 1220000000.0,
    "putthroughValue": 0.0,
    "buyForeignQuantity": 4840.0,
    "buyForeignValue": 34220000.0,
    "sellForeignQuantity": 6370.0,
    "sellForeignValue": 45060000.0,
    "buyCount": 308.0,
    "buyQuantity": 402600.0,
    "sellCount": 162.0,
    "sellQuantity": 539590.0,
    "adjRatio": 1.5990314191472081,
    "currentForeignRoom": 23437681.0,
    "propTradingNetDealValue": null,
    "propTradingNetPTValue": null,
    "propTradingNetValue": null,
    "unit": 1000.0
  },
  {
    "date": "2020-08-05T00:00:00",
    "symbol": "TVB",
    "priceHigh": 7.3,
    "priceLow": 6.9,
    "priceOpen": 7.06,
    "priceAverage": 7.153008053055424,
    "priceClose": 7.2,
    "priceBasic": 7.25,
    "totalVolume": 295540.0,
    "dealVolume": 295540.0,
    "putthroughVolume": 0.0,
    "totalValue": 2114000000.0,
    "putthroughValue": 0.0,
    "buyForeignQuantity": 5660.0,
    "buyForeignValue": 40820000.0,
    "sellForeignQuantity": 10000.0,
    "sellForeignValue": 73000000.0,
    "buyCount": 283.0,
    "buyQuantity": 547000.0,
    "sellCount": 202.0,
    "sellQuantity": 569490.0,
    "adjRatio": 1.5990314191472081,
    "currentForeignRoom": 23435011.0,
    "propTradingNetDealValue": null,
    "propTradingNetPTValue": null,
    "propTradingNetValue": null,
    "unit": 1000.0
  },
  {
    "date": "2020-08-04T00:00:00",
    "symbol": "TVB",
    "priceHigh": 7.5,
    "priceLow": 7.12,
    "priceOpen": 7.13,
    "priceAverage": 7.2197988070862635,
    "priceClose": 7.25,
    "priceBasic": 7.12,
    "totalVolume": 449320.0,
    "dealVolume": 449320.0,
    "putthroughVolume": 0.0,
    "totalValue": 3244000000.0,
    "putthroughValue": 0.0,
    "buyForeignQuantity": 8840.0,
    "buyForeignValue": 64370000.0,
    "sellForeignQuantity": 160.0,
    "sellForeignValue": 1170000.0,
    "buyCount": 389.0,
    "buyQuantity": 892460.0,
    "sellCount": 248.0,
    "sellQuantity": 866570.0,
    "adjRatio": 1.5990314191472081,
    "currentForeignRoom": 23432631.0,
    "propTradingNetDealValue": null,
    "propTradingNetPTValue": null,
    "propTradingNetValue": null,
    "unit": 1000.0
  },
  {
    "date": "2020-08-03T00:00:00",
    "symbol": "TVB",
    "priceHigh": 7.2,
    "priceLow": 6.9,
    "priceOpen": 6.9,
    "priceAverage": 7.149648222095456,
    "priceClose": 7.12,
    "priceBasic": 6.97,
    "totalVolume": 262950.0,
    "dealVolume": 262950.0,
    "putthroughVolume": 0.0,
    "totalValue": 1880000000.0,
    "putthroughValue": 0.0,
    "buyForeignQuantity": 11040.0,
    "buyForeignValue": 78660000.0,
    "sellForeignQuantity": 7510.0,
    "sellForeignValue": 53870000.0,
    "buyCount": 258.0,
    "buyQuantity": 690380.0,
    "sellCount": 185.0,
    "sellQuantity": 594430.0,
    "adjRatio": 1.5990314191472081,
    "currentForeignRoom": 23436471.0,
    "propTradingNetDealValue": null,
    "propTradingNetPTValue": null,
    "propTradingNetValue": null,
    "unit": 1000.0
  }
]