[
  {
    "date": "2021-10-29T00:00:00",
    "symbol": "KHG",
    "priceHigh": 17.85,
    "priceLow": 17.0,
    "priceOpen": 17.8,
    "priceAverage": 17.69290322580645,
    "priceClose": 17.5,
    "priceBasic": 16.7,
    "totalVolume": 6200000.0,
    "dealVolume": 6200000.0,
    "putthroughVolume": 0.0,
    "totalValue": 109696000000.0,
    "putthroughValue": 0.0,
    "buyForeignQuantity": 30000.0,
    "buyForeignValue": 535500000.0,
    "sellForeignQuantity": 16400.0,
    "sellForeignValue": 291920000.0,
    "buyCount": 3973.0,
    "buyQuantity": 8641800.0,
    "sellCount": 2410.0,
    "sellQuantity": 9389600.0,
    "adjRatio": 1.39,
    "currentForeignRoom": 85566598.0,
    "propTradingNetDealValue": 0.0,
    "propTradingNetPTValue": 0.0,
    "propTradingNetValue": 0.0,
    "unit": 1000.0
  },
  {
    "date": "2021-10-28T00:00:00",
    "symbol": "KHG",
    "priceHigh": 16.7,
    "priceLow": 16.0,
    "priceOpen": 16.7,
    "priceAverage": 16.6648114651454,
    "priceClose": 16.7,
    "priceBasic": 15.65,
    "totalVolume": 2156100.0,
    "dealVolume": 2156100.0,
    "putthroughVolume": 0.0,
    "totalValue": 35931000000.0,
    "putthroughValue": 0.0,
    "buyForeignQuantity": 100.0,
    "buyForeignValue": 1670000.0,
    "sellForeignQuantity": 17900.0,
    "sellForeignValue": 298930000.0,
    "buyCount": 2142.0,
    "buyQuantity": 5670500.0,
    "sellCount": 616.0,
    "sellQuantity": 2316600.0,
    "adjRatio": 1.39,
    "currentForeignRoom": 85596598.0,
    "propTradingNetDealValue": 0.0,
    "propTradingNetPTValue": 0.0,
    "propTradingNetValue": 0.0,
    "unit": 1000.0
  },
  {
    "date": "2021-10-27T00:00:00",
    "symbol": "KHG",
    "priceHigh": 15.65,
    "priceLow": 14.85,
    "priceOpen": 14.85,
    "priceAverage": 15.492228055215051,
    "priceClose": 15.65,
    "priceBasic": 14.65,
    "totalVolume": 3752600.0,
    "dealVolume": 3752600.0,
    "putthroughVolume": 0.0,
    "totalValue": 58136135000.0,
    "putthroughValue": 0.0,
    "buyForeignQuantity": 10000.0,
    "buyForeignValue": 156500000.0,
    "sellForeignQuantity": 0.0,
    "sellForeignValue": 0.0,
    "buyCount": 2065.0,
    "buyQuantity": 7524700.0,
    "sellCount": 1103.0,
    "sellQuantity": 3998000.0,
    "adjRatio": 1.39,
    "currentForeignRoom": 85596698.0,
    "propTradingNetDealValue": 0.0,
    "propTradingNetPTValue": 0.0,
    "propTradingNetValue": 0.0,
    "unit": 1000.0
  },
  {
    "date": "2021-10-26T00:00:00",
    "symbol": "KHG",
    "priceHigh": 14.8,
    "priceLow": 14.3,
    "priceOpen": 14.7,
    "priceAverage": 14.576484018264841,
    "priceClose": 14.65,
    "priceBasic": 14.7,
    "totalVolume": 876000.0,
    "dealVolume": 876000.0,
    "putthroughVolume": 0.0,
    "totalValue": 12769000000.0,
    "putthroughValue": 0.0,
    "buyForeignQuantity": 0.0,
    "buyForeignValue": 0.0,
    "sellForeignQuantity": 0.0,
    "sellForeignValue": 0.0,
    "buyCount": 739.0,
    "buyQuantity": 1320800.0,
    "sellCount": 653.0,
    "sellQuantity": 2070100.0,
    "adjRatio": 1.39,
    "currentForeignRoom": 85605698.0,
    "propTradingNetDealValue": 0.0,
    "propTradingNetPTValue": 0.0,
    "propTradingNetValue": 0.0,
    "unit": 1000.0
  },
  {
    "date": "2021-10-25T00:00:00",
    "symbol": "KHG",
    "priceHigh": 15.05,
    "priceLow": 14.6,
    "priceOpen": 15.05,
    "priceAverage": 14.738885711951637,
    "priceClose": 14.7,
    "priceBasic": 14.75,
    "totalVolume": 1224100.0,
    "dealVolume": 1224100.0,
    "putthroughVolume": 0.0,
    "totalValue": 18041870000.0,
    "putthroughValue": 0.0,
    "buyForeignQuantity": 0.0,
    "buyForeignValue": 0.0,
    "sellForeignQuantity": 0.0,
    "sellForeignValue": 0.0,
    "buyCount": 692.0,
    "buyQuantity": 1642600.0,
    "sellCount": 878.0,
    "sellQuantity": 2642600.0,
    "adjRatio": 1.39,
    "currentForeignRoom": 85605698.0,
    "propTradingNetDealValue": 0.0,
    "propTradingNetPTValue": 0.0,
    "propTradingNetValue": 0.0,
    "unit": 1000.0
  },
  {
    "date": "2021-10-22T00:00:00",
    "symbol": "KHG",
    "priceHigh": 15.0,
    "priceLow": 14.2,
    "priceOpen": 14.4,
    "priceAverage": 14.599729648543105,
    "priceClose": 14.75,
    "priceBasic": 14.5,
    "totalVolume": 1331600.0,
    "dealVolume": 1331600.0,
    "putthroughVolume": 0.0,
    "totalValue": 19441000000.0,
    "putthroughValue": 0.0,
    "buyForeignQuantity": 0.0,
    "buyForeignValue": 0.0,
    "sellForeignQuantity": 1000.0,
    "sellForeignValue": 14450000.0,
    "buyCount": 1034.0,
    "buyQuantity": 2149600.0,
    "sellCount": 1067.0,
    "sellQuantity": 2737400.0,
    "adjRatio": 1.39,
    "currentForeignRoom": 85605698.0,
    "propTradingNetDealValue": 0.0,
    "propTradingNetPTValue": 0.0,
    "propTradingNetValue": 0.0,
    "unit": 1000.0
  },
  {
    "date": "2021-10-21T00:00:00",
    "symbol": "KHG",
    "priceHigh": 14.6,
    "priceLow": 14.1,
    "priceOpen": 14.4,
    "priceAverage": 14.303950698800485,
    "priceClose": 14.5,
    "priceBasic": 14.3,
    "totalVolume": 908700.0,
    "dealVolume": 908700.0,
    "putthroughVolume": 0.0,
    "totalValue": 12998000000.0,
    "putthroughValue": 0.0,
    "buyForeignQuantity": 0.0,
    "buyForeignValue": 0.0,
    "sellForeignQuantity": 0.0,
    "sellForeignValue": 0.0,
    "buyCount": 688.0,
    "buyQuantity": 1475300.0,
    "sellCount": 619.0,
    "sellQuantity": 1557800.0,
    "adjRatio": 1.39,
    "currentForeignRoom": 85605698.0,
    "propTradingNetDealValue": 0.0,
    "propTradingNetPTValue": 0.0,
    "propTradingNetValue": 0.0,
    "unit": 1000.0
  },
  {
    "date": "2021-10-20T00:00:00",
    "symbol": "KHG",
    "priceHigh": 14.5,
    "priceLow": 13.9,
    "priceOpen": 14.3,
    "priceAverage": 14.130314743235783,
    "priceClose": 14.3,
    "priceBasic": 14.2,
    "totalVolume": 1086600.0,
    "dealVolume": 1086600.0,
    "putthroughVolume": 0.0,
    "totalValue": 15354000000.0,
    "putthroughValue": 0.0,
    "buyForeignQuantity": 4800.0,
    "buyForeignValue": 68640000.0,
    "sellForeignQuantity": 0.0,
    "sellForeignValue": 0.0,
    "buyCount": 804.0,
    "buyQuantity": 1638400.0,
    "sellCount": 617.0,
    "sellQuantity": 1767300.0,
    "adjRatio": 1.39,
    "currentForeignRoom": 85605698.0,
    "propTradingNetDealValue": 0.0,
    "propTradingNetPTValue": 0.0,
    "propTradingNetValue": 0.0,
    "unit": 1000.0
  },
  {
    "date": "2021-10-19T00:00:00",
    "symbol": "KHG",
    "priceHigh": 14.5,
    "priceLow": 13.8,
    "priceOpen": 14.05,
    "priceAverage": 14.04040404040404,
    "priceClose": 14.2,
    "priceBasic": 14.3,
    "totalVolume": 1306800.0,
    "dealVolume": 1306800.0,
    "putthroughVolume": 0.0,
    "totalValue": 18348000000.0,
    "putthroughValue": 0.0,
    "buyForeignQuantity": 1000.0,
    "buyForeignValue": 13930000.0,
    "sellForeignQuantity": 0.0,
    "sellForeignValue": 0.0,
    "buyCount": 1212.0,
    "buyQuantity": 2058100.0,
    "sellCount": 572.0,
    "sellQuantity": 2295800.0,
    "adjRatio": 1.39,
    "currentForeignRoom": 85610498.0,
    "propTradingNetDealValue": 0.0,
    "propTradingNetPTValue": 0.0,
    "propTradingNetValue": 0.0,
    "unit": 1000.0
  },
  {
    "date": "2021-10-18T00:00:00",
    "symbol": "KHG",
    "priceHigh": 14.7,
    "priceLow": 14.15,
    "priceOpen": 14.7,
    "priceAverage": 14.376155268022181,
    "priceClose": 14.3,
    "priceBasic": 14.8,
    "totalVolume": 1127000.0,
    "dealVolume": 1082000.0,
    "putthroughVolume": 45000.0,
    "totalValue": 16221000000.0,
    "putthroughValue": 666000000.0,
    "buyForeignQuantity": 0.0,
    "buyForeignValue": 0.0,
    "sellForeignQuantity": 0.0,
    "sellForeignValue": 0.0,
    "buyCount": 696.0,
    "buyQuantity": 1388000.0,
    "sellCount": 721.0,
    "sellQuantity": 2474900.0,
    "adjRatio": 1.39,
    "currentForeignRoom": 85611498.0,
    "propTradingNetDealValue": null,
    "propTradingNetPTValue": null,
    "propTradingNetValue": null,
    "unit": 1000.0
  },
  {
    "date": "2021-10-15T00:00:00",
    "symbol": "KHG",
    "priceHigh": 15.35,
    "priceLow": 14.55,
    "priceOpen": 15.0,
    "priceAverage": 14.907190243248676,
    "priceClose": 14.8,
    "priceBasic": 14.65,
    "totalVolume": 1562300.0,
    "dealVolume": 1492300.0,
    "putthroughVolume": 70000.0,
    "totalValue": 23271500000.0,
    "putthroughValue": 1025500000.0,
    "buyForeignQuantity": 0.0,
    "buyForeignValue": 0.0,
    "sellForeignQuantity": 0.0,
    "sellForeignValue": 0.0,
    "buyCount": 1015.0,
    "buyQuantity": 2127700.0,
    "sellCount": 1456.0,
    "sellQuantity": 3840100.0,
    "adjRatio": 1.39,
    "currentForeignRoom": 85611498.0,
    "propTradingNetDealValue": 0.0,
    "propTradingNetPTValue": 0.0,
    "propTradingNetValue": 0.0,
    "unit": 1000.0
  },
  {
    "date": "2021-10-14T00:00:00",
    "symbol": "KHG",
    "priceHigh": 14.65,
    "priceLow": 13.55,
    "priceOpen": 13.75,
    "priceAverage": 14.11583242113643,
    "priceClose": 14.65,
    "priceBasic": 13.7,
    "totalVolume": 2009800.0,
    "dealVolume": 2009800.0,
    "putthroughVolume": 0.0,
    "totalValue": 28370000000.0,
    "putthroughValue": 0.0,
    "buyForeignQuantity": 0.0,
    "buyForeignValue": 0.0,
    "sellForeignQuantity": 0.0,
    "sellForeignValue": 0.0,
    "buyCount": 1161.0,
    "buyQuantity": 3517000.0,
    "sellCount": 713.0,
    "sellQuantity": 2410900.0,
    "adjRatio": 1.39,
    "currentForeignRoom": 85611498.0,
    "propTradingNetDealValue": 0.0,
    "propTradingNetPTValue": 0.0,
    "propTradingNetValue": 0.0,
    "unit": 1000.0
  },
  {
    "date": "2021-10-13T00:00:00",
    "symbol": "KHG",
    "priceHigh": 13.8,
    "priceLow": 13.55,
    "priceOpen": 13.65,
    "priceAverage": 13.68564870477648,
    "priceClose": 13.7,
    "priceBasic": 13.7,
    "totalVolume": 914900.0,
    "dealVolume": 914900.0,
    "putthroughVolume": 0.0,
    "totalValue": 12521000000.0,
    "putthroughValue": 0.0,
    "buyForeignQuantity": 0.0,
    "buyForeignValue": 0.0,
    "sellForeignQuantity": 0.0,
    "sellForeignValue": 0.0,
    "buyCount": 613.0,
    "buyQuantity": 1243100.0,
    "sellCount": 508.0,
    "sellQuantity": 1603600.0,
    "adjRatio": 1.39,
    "currentForeignRoom": 85611498.0,
    "propTradingNetDealValue": 0.0,
    "propTradingNetPTValue": 0.0,
    "propTradingNetValue": 0.0,
    "unit": 1000.0
  },
  {
    "date": "2021-10-12T00:00:00",
    "symbol": "KHG",
    "priceHigh": 13.9,
    "priceLow": 13.55,
    "priceOpen": 13.85,
    "priceAverage": 13.691315563198625,
    "priceClose": 13.7,
    "priceBasic": 13.85,
    "totalVolume": 1163000.0,
    "dealVolume": 1163000.0,
    "putthroughVolume": 0.0,
    "totalValue": 15923000000.0,
    "putthroughValue": 0.0,
    "buyForeignQuantity": 0.0,
    "buyForeignValue": 0.0,
    "sellForeignQuantity": 0.0,
    "sellForeignValue": 0.0,
    "buyCount": 891.0,
    "buyQuantity": 1613200.0,
    "sellCount": 404.0,
    "sellQuantity": 1949500.0,
    "adjRatio": 1.39,
    "currentForeignRoom": 85611498.0,
    "propTradingNetDealValue": 0.0,
    "propTradingNetPTValue": 0.0,
    "propTradingNetValue": 0.0,
    "unit": 1000.0
  },
  {
    "date": "2021-10-11T00:00:00",
    "symbol": "KHG",
    "priceHigh": 14.0,
    "priceLow": 13.75,
    "priceOpen": 13.8,
    "priceAverage": 13.84225352112676,
    "priceClose": 13.85,
    "priceBasic": 13.9,
    "totalVolume": 1065000.0,
    "dealVolume": 1065000.0,
    "putthroughVolume": 0.0,
    "totalValue": 14742000000.0,
    "putthroughValue": 0.0,
    "buyForeignQuantity": 0.0,
    "buyForeignValue": 0.0,
    "sellForeignQuantity": 0.0,
    "sellForeignValue": 0.0,
    "buyCount": 767.0,
    "buyQuantity": 1484900.0,
    "sellCount": 449.0,
    "sellQuantity": 1824500.0,
    "adjRatio": 1.39,
    "currentForeignRoom": 85611498.0,
    "propTradingNetDealValue": 0.0,
    "propTradingNetPTValue": 0.0,
    "propTradingNetValue": 0.0,
    "unit": 1000.0
  },
  {
    "date": "2021-10-08T00:00:00",
    "symbol": "KHG",
    "priceHigh": 14.05,
    "priceLow": 13.75,
    "priceOpen": 14.05,
    "priceAverage": 13.936912374697545,
    "priceClose": 13.9,
    "priceBasic": 14.0,
    "totalVolume": 1657200.0,
    "dealVolume": 1157200.0,
    "putthroughVolume": 500000.0,
    "totalValue": 23127795000.0,
    "putthroughValue": 7000000000.0,
    "buyForeignQuantity": 0.0,
    "buyForeignValue": 0.0,
    "sellForeignQuantity": 0.0,
    "sellForeignValue": 0.0,
    "buyCount": 610.0,
    "buyQuantity": 1545000.0,
    "sellCount": 541.0,
    "sellQuantity": 1989100.0,
    "adjRatio": 1.39,
    "currentForeignRoom": 85610498.0,
    "propTradingNetDealValue": 0.0,
    "propTradingNetPTValue": 0.0,
    "propTradingNetValue": 0.0,
    "unit": 1000.0
  },
  {
    "date": "2021-10-07T00:00:00",
    "symbol": "KHG",
    "priceHigh": 14.2,
    "priceLow": 13.8,
    "priceOpen": 14.15,
    "priceAverage": 13.969616908850726,
    "priceClose": 14.0,
    "priceBasic": 14.05,
    "totalVolume": 1259800.0,
    "dealVolume": 1059800.0,
    "putthroughVolume": 200000.0,
    "totalValue": 17615000000.0,
    "putthroughValue": 2810000000.0,
    "buyForeignQuantity": 0.0,
    "buyForeignValue": 0.0,
    "sellForeignQuantity": 0.0,
    "sellForeignValue": 0.0,
    "buyCount": 682.0,
    "buyQuantity": 1509100.0,
    "sellCount": 584.0,
    "sellQuantity": 1917700.0,
    "adjRatio": 1.39,
    "currentForeignRoom": 85574798.0,
    "propTradingNetDealValue": 0.0,
    "propTradingNetPTValue": 0.0,
    "propTradingNetValue": 0.0,
    "unit": 1000.0
  },
  {
    "date": "2021-10-06T00:00:00",
    "symbol": "KHG",
    "priceHigh": 14.3,
    "priceLow": 13.85,
    "priceOpen": 14.0,
    "priceAverage": 13.976335664335664,
    "priceClose": 14.05,
    "priceBasic": 13.95,
    "totalVolume": 1072500.0,
    "dealVolume": 1072500.0,
    "putthroughVolume": 0.0,
    "totalValue": 14989620000.0,
    "putthroughValue": 0.0,
    "buyForeignQuantity": 0.0,
    "buyForeignValue": 0.0,
    "sellForeignQuantity": 1000.0,
    "sellForeignValue": 13950000.0,
    "buyCount": 512.0,
    "buyQuantity": 1440600.0,
    "sellCount": 511.0,
    "sellQuantity": 1613600.0,
    "adjRatio": 1.39,
    "currentForeignRoom": 85574798.0,
    "propTradingNetDealValue": 0.0,
    "propTradingNetPTValue": 0.0,
    "propTradingNetValue": 0.0,
    "unit": 1000.0
  },
  {
    "date": "2021-10-05T00:00:00",
    "symbol": "KHG",
    "priceHigh": 14.1,
    "priceLow": 13.6,
    "priceOpen": 13.8,
    "priceAverage": 13.830963665086887,
    "priceClose": 13.95,
    "priceBasic": 13.8,
    "totalVolume": 1359400.0,
    "dealVolume": 1139400.0,
    "putthroughVolume": 220000.0,
    "totalValue": 18795000000.0,
    "putthroughValue": 3036000000.0,
    "buyForeignQuantity": 0.0,
    "buyForeignValue": 0.0,
    "sellForeignQuantity": 35700.0,
    "sellForeignValue": 495630000.0,
    "buyCount": 458.0,
    "buyQuantity": 1512800.0,
    "sellCount": 597.0,
    "sellQuantity": 1795500.0,
    "adjRatio": 1.39,
    "currentForeignRoom": 85574798.0,
    "propTradingNetDealValue": 0.0,
    "propTradingNetPTValue": 0.0,
    "propTradingNetValue": 0.0,
    "unit": 1000.0
  },
  {
    "date": "2021-10-04T00:00:00",
    "symbol": "KHG",
    "priceHigh": 14.0,
    "priceLow": 13.4,
    "priceOpen": 13.9,
    "priceAverage": 13.644721233689204,
    "priceClose": 13.8,
    "priceBasic": 13.9,
    "totalVolume": 1011600.0,
    "dealVolume": 1011600.0,
    "putthroughVolume": 0.0,
    "totalValue": 13803000000.0,
    "putthroughValue": 0.0,
    "buyForeignQuantity": 0.0,
    "buyForeignValue": 0.0,
    "sellForeignQuantity": 0.0,
    "sellForeignValue": 0.0,
    "buyCount": 609.0,
    "buyQuantity": 1296900.0,
    "sellCount": 441.0,
    "sellQuantity": 1658700.0,
    "adjRatio": 1.39,
    "currentForeignRoom": 85574798.0,
    "propTradingNetDealValue": 0.0,
    "propTradingNetPTValue": 0.0,
    "propTradingNetValue": 0.0,
    "unit": 1000.0
  },
  {
    "date": "2021-10-01T00:00:00",
    "symbol": "KHG",
    "priceHigh": 14.4,
    "priceLow": 13.7,
    "priceOpen": 14.3,
    "priceAverage": 13.979900700934579,
    "priceClose": 13.9,
    "priceBasic": 14.1,
    "totalVolume": 856000.0,
    "dealVolume": 856000.0,
    "putthroughVolume": 0.0,
    "totalValue": 11966795000.0,
    "putthroughValue": 0.0,
    "buyForeignQuantity": 200.0,
    "buyForeignValue": 2780000.0,
    "sellForeignQuantity": 0.0,
    "sellForeignValue": 0.0,
    "buyCount": 590.0,
    "buyQuantity": 1165200.0,
    "sellCount": 567.0,
    "sellQuantity": 1660500.0,
    "adjRatio": 1.39,
    "currentForeignRoom": 85574798.0,
    "propTradingNetDealValue": 0.0,
    "propTradingNetPTValue": 0.0,
    "propTradingNetValue": 0.0,
    "unit": 1000.0
  }
]