[
  {
    "date": "2025-04-29T00:00:00",
    "symbol": "ACC",
    "priceHigh": 14.15,
    "priceLow": 13.95,
    "priceOpen": 14.1,
    "priceAverage": 14.008963963963964,
    "priceClose": 14.15,
    "priceBasic": 14.1,
    "totalVolume": 222000.0,
    "dealVolume": 222000.0,
    "putthroughVolume": 0.0,
    "totalValue": 3109990000.0,
    "putthroughValue": 0.0,
    "buyForeignQuantity": 0.0,
    "buyForeignValue": 0.0,
    "sellForeignQuantity": 0.0,
    "sellForeignValue": 0.0,
    "buyCount": 64.0,
    "buyQuantity": 290179.0,
    "sellCount": 64.0,
    "sellQuantity": 328304.0,
    "adjRatio": 1.0,
    "currentForeignRoom": 0.0,
    "propTradingNetDealValue": 0.0,
    "propTradingNetPTValue": 0.0,
    "propTradingNetValue": 0.0,
    "unit": 1000.0
  },
  {
    "date": "2025-04-28T00:00:00",
    "symbol": "ACC",
    "priceHigh": 14.1,
    "priceLow": 14.0,
    "priceOpen": 14.0,
    "priceAverage": 14.076991150442478,
    "priceClose": 14.1,
    "priceBasic": 14.1,
    "totalVolume": 11300.0,
    "dealVolume": 11300.0,
    "putthroughVolume": 0.0,
    "totalValue": 159070000.0,
    "putthroughValue": 0.0,
    "buyForeignQuantity": 0.0,
    "buyForeignValue": 0.0,
    "sellForeignQuantity": 0.0,
    "sellForeignValue": 0.0,
    "buyCount": 45.0,
    "buyQuantity": 85344.0,
    "sellCount": 59.0,
    "sellQuantity": 107510.0,
    "adjRatio": 1.0,
    "currentForeignRoom": 0.0,
    "propTradingNetDealValue": 0.0,
    "propTradingNetPTValue": 0.0,
    "propTradingNetValue": 0.0,
    "unit": 1000.0
  },
  {
    "date": "2025-04-25T00:00:00",
    "symbol": "ACC",
    "priceHigh": 14.1,
    "priceLow": 14.0,
    "priceOpen": 14.0,
    "priceAverage": 14.095901639344262,
    "priceClose": 14.1,
    "priceBasic": 14.1,
    "totalVolume": 12200.0,
    "dealVolume": 12200.0,
    "putthroughVolume": 0.0,
    "totalValue": 171970000.0,
    "putthroughValue": 0.0,
    "buyForeignQuantity": 0.0,
    "buyForeignValue": 0.0,
    "sellForeignQuantity": 0.0,
    "sellForeignValue": 0.0,
    "buyCount": 43.0,
    "buyQuantity": 63523.0,
    "sellCount": 51.0,
    "sellQuantity": 519081.0,
    "adjRatio": 1.0,
    "currentForeignRoom": 0.0,
    "propTradingNetDealValue": 0.0,
    "propTradingNetPTValue": 0.0,
    "propTradingNetValue": 0.0,
    "unit": 1000.0
  },
  {
    "date": "2025-04-24T00:00:00",
    "symbol": "ACC",
    "priceHigh": 14.1,
    "priceLow": 13.9,
    "priceOpen": 14.05,
    "priceAverage": 14.02917808219178,
    "priceClose": 14.1,
    "priceBasic": 14.0,
    "totalVolume": 36500.0,
    "dealVolume": 36500.0,
    "putthroughVolume": 0.0,
    "totalValue": 512065000.0,
    "putthroughValue": 0.0,
    "buyForeignQuantity": 0.0,
    "buyForeignValue": 0.0,
    "sellForeignQuantity": 0.0,
    "sellForeignValue": 0.0,
    "buyCount": 54.0,
    "buyQuantity": 120680.0,
    "sellCount": 66.0,
    "sellQuantity": 139772.0,
    "adjRatio": 1.0,
    "currentForeignRoom": 0.0,
    "propTradingNetDealValue": 0.0,
    "propTradingNetPTValue": 0.0,
    "propTradingNetValue": 0.0,
    "unit": 1000.0
  },
  {
    "date": "2025-04-23T00:00:00",
    "symbol": "ACC",
    "priceHigh": 14.15,
    "priceLow": 13.9,
    "priceOpen": 13.9,
    "priceAverage": 14.021178343949044,
    "priceClose": 14.0,
    "priceBasic": 14.1,
    "totalVolume": 31400.0,
    "dealVolume": 31400.0,
    "putthroughVolume": 0.0,
    "totalValue": 440265000.0,
    "putthroughValue": 0.0,
    "buyForeignQuantity": 0.0,
    "buyForeignValue": 0.0,
    "sellForeignQuantity": 0.0,
    "sellForeignValue": 0.0,
    "buyCount": 74.0,
    "buyQuantity": 104903.0,
    "sellCount": 81.0,
    "sellQuantity": 142594.0,
    "adjRatio": 1.0,
    "currentForeignRoom": 0.0,
    "propTradingNetDealValue": 0.0,
    "propTradingNetPTValue": 0.0,
    "propTradingNetValue": 0.0,
    "unit": 1000.0
  },
  {
    "date": "2025-04-22T00:00:00",
    "symbol": "ACC",
    "priceHigh": 14.15,
    "priceLow": 13.7,
    "priceOpen": 14.0,
    "priceAverage": 13.908698940998487,
    "priceClose": 14.1,
    "priceBasic": 14.15,
    "totalVolume": 132200.0,
    "dealVolume": 132200.0,
    "putthroughVolume": 0.0,
    "totalValue": 1838730000.0,
    "putthroughValue": 0.0,
    "buyForeignQuantity": 0.0,
    "buyForeignValue": 0.0,
    "sellForeignQuantity": 0.0,
    "sellForeignValue": 0.0,
    "buyCount": 77.0,
    "buyQuantity": 178067.0,
    "sellCount": 81.0,
    "sellQuantity": 227100.0,
    "adjRatio": 1.0,
    "currentForeignRoom": 0.0,
    "propTradingNetDealValue": 0.0,
    "propTradingNetPTValue": 0.0,
    "propTradingNetValue": 0.0,
    "unit": 1000.0
  },
  {
    "date": "2025-04-21T00:00:00",
    "symbol": "ACC",
    "priceHigh": 14.25,
    "priceLow": 13.95,
    "priceOpen": 14.1,
    "priceAverage": 14.06421821305842,
    "priceClose": 14.15,
    "priceBasic": 14.25,
    "totalVolume": 116400.0,
    "dealVolume": 116400.0,
    "putthroughVolume": 0.0,
    "totalValue": 1637075000.0,
    "putthroughValue": 0.0,
    "buyForeignQuantity": 0.0,
    "buyForeignValue": 0.0,
    "sellForeignQuantity": 0.0,
    "sellForeignValue": 0.0,
    "buyCount": 86.0,
    "buyQuantity": 228886.0,
    "sellCount": 136.0,
    "sellQuantity": 462407.0,
    "adjRatio": 1.0,
    "currentForeignRoom": 0.0,
    "propTradingNetDealValue": 0.0,
    "propTradingNetPTValue": 0.0,
    "propTradingNetValue": 0.0,
    "unit": 1000.0
  },
  {
    "date": "2025-04-18T00:00:00",
    "symbol": "ACC",
    "priceHigh": 14.25,
    "priceLow": 13.9,
    "priceOpen": 14.25,
    "priceAverage": 14.016373655208607,
    "priceClose": 14.25,
    "priceBasic": 14.25,
    "totalVolume": 762200.0,
    "dealVolume": 762200.0,
    "putthroughVolume": 0.0,
    "totalValue": 10683280000.0,
    "putthroughValue": 0.0,
    "buyForeignQuantity": 0.0,
    "buyForeignValue": 0.0,
    "sellForeignQuantity": 0.0,
    "sellForeignValue": 0.0,
    "buyCount": 130.0,
    "buyQuantity": 847798.0,
    "sellCount": 179.0,
    "sellQuantity": 1153313.0,
    "adjRatio": 1.0,
    "currentForeignRoom": 0.0,
    "propTradingNetDealValue": 0.0,
    "propTradingNetPTValue": 0.0,
    "propTradingNetValue": 0.0,
    "unit": 1000.0
  },
  {
    "date": "2025-04-17T00:00:00",
    "symbol": "ACC",
    "priceHigh": 14.25,
    "priceLow": 13.9,
    "priceOpen": 13.9,
    "priceAverage": 13.963537644787644,
    "priceClose": 14.25,
    "priceBasic": 14.25,
    "totalVolume": 207200.0,
    "dealVolume": 207200.0,
    "putthroughVolume": 0.0,
    "totalValue": 2893245000.0,
    "putthroughValue": 0.0,
    "buyForeignQuantity": 0.0,
    "buyForeignValue": 0.0,
    "sellForeignQuantity": 0.0,
    "sellForeignValue": 0.0,
    "buyCount": 95.0,
    "buyQuantity": 434378.0,
    "sellCount": 77.0,
    "sellQuantity": 319757.0,
    "adjRatio": 1.0,
    "currentForeignRoom": 0.0,
    "propTradingNetDealValue": 0.0,
    "propTradingNetPTValue": 0.0,
    "propTradingNetValue": 0.0,
    "unit": 1000.0
  },
  {
    "date": "2025-04-16T00:00:00",
    "symbol": "ACC",
    "priceHigh": 14.3,
    "priceLow": 13.8,
    "priceOpen": 13.9,
    "priceAverage": 14.019863157894736,
    "priceClose": 14.25,
    "priceBasic": 14.3,
    "totalVolume": 1425000.0,
    "dealVolume": 1425000.0,
    "putthroughVolume": 0.0,
    "totalValue": 19978305000.0,
    "putthroughValue": 0.0,
    "buyForeignQuantity": 0.0,
    "buyForeignValue": 0.0,
    "sellForeignQuantity": 0.0,
    "sellForeignValue": 0.0,
    "buyCount": 176.0,
    "buyQuantity": 1562452.0,
    "sellCount": 184.0,
    "sellQuantity": 1924601.0,
    "adjRatio": 1.0,
    "currentForeignRoom": 0.0,
    "propTradingNetDealValue": 0.0,
    "propTradingNetPTValue": 0.0,
    "propTradingNetValue": 0.0,
    "unit": 1000.0
  },
  {
    "date": "2025-04-15T00:00:00",
    "symbol": "ACC",
    "priceHigh": 14.3,
    "priceLow": 13.95,
    "priceOpen": 14.3,
    "priceAverage": 14.130960854092528,
    "priceClose": 14.3,
    "priceBasic": 14.3,
    "totalVolume": 56200.0,
    "dealVolume": 56200.0,
    "putthroughVolume": 0.0,
    "totalValue": 794160000.0,
    "putthroughValue": 0.0,
    "buyForeignQuantity": 0.0,
    "buyForeignValue": 0.0,
    "sellForeignQuantity": 0.0,
    "sellForeignValue": 0.0,
    "buyCount": 120.0,
    "buyQuantity": 184642.0,
    "sellCount": 108.0,
    "sellQuantity": 168919.0,
    "adjRatio": 1.0,
    "currentForeignRoom": 0.0,
    "propTradingNetDealValue": 0.0,
    "propTradingNetPTValue": 0.0,
    "propTradingNetValue": 0.0,
    "unit": 1000.0
  },
  {
    "date": "2025-04-14T00:00:00",
    "symbol": "ACC",
    "priceHigh": 14.3,
    "priceLow": 13.8,
    "priceOpen": 14.3,
    "priceAverage": 14.17931090262051,
    "priceClose": 14.3,
    "priceBasic": 14.3,
    "totalVolume": 618200.0,
    "dealVolume": 618200.0,
    "putthroughVolume": 0.0,
    "totalValue": 8765650000.0,
    "putthroughValue": 0.0,
    "buyForeignQuantity": 0.0,
    "buyForeignValue": 0.0,
    "sellForeignQuantity": 0.0,
    "sellForeignValue": 0.0,
    "buyCount": 124.0,
    "buyQuantity": 737649.0,
    "sellCount": 207.0,
    "sellQuantity": 925839.0,
    "adjRatio": 1.0,
    "currentForeignRoom": 0.0,
    "propTradingNetDealValue": 0.0,
    "propTradingNetPTValue": 0.0,
    "propTradingNetValue": 0.0,
    "unit": 1000.0
  },
  {
    "date": "2025-04-11T00:00:00",
    "symbol": "ACC",
    "priceHigh": 14.35,
    "priceLow": 13.7,
    "priceOpen": 13.7,
    "priceAverage": 14.109898882384247,
    "priceClose": 14.3,
    "priceBasic": 14.35,
    "totalVolume": 187900.0,
    "dealVolume": 187900.0,
    "putthroughVolume": 0.0,
    "totalValue": 2651250000.0,
    "putthroughValue": 0.0,
    "buyForeignQuantity": 0.0,
    "buyForeignValue": 0.0,
    "sellForeignQuantity": 0.0,
    "sellForeignValue": 0.0,
    "buyCount": 137.0,
    "buyQuantity": 284899.0,
    "sellCount": 255.0,
    "sellQuantity": 569322.0,
    "adjRatio": 1.0,
    "currentForeignRoom": 0.0,
    "propTradingNetDealValue": 0.0,
    "propTradingNetPTValue": 0.0,
    "propTradingNetValue": 0.0,
    "unit": 1000.0
  },
  {
    "date": "2025-04-10T00:00:00",
    "symbol": "ACC",
    "priceHigh": 14.95,
    "priceLow": 13.55,
    "priceOpen": 14.6,
    "priceAverage": 14.499383561643835,
    "priceClose": 14.35,
    "priceBasic": 14.3,
    "totalVolume": 73000.0,
    "dealVolume": 73000.0,
    "putthroughVolume": 0.0,
    "totalValue": 1058455000.0,
    "putthroughValue": 0.0,
    "buyForeignQuantity": 0.0,
    "buyForeignValue": 0.0,
    "sellForeignQuantity": 0.0,
    "sellForeignValue": 0.0,
    "buyCount": 244.0,
    "buyQuantity": 314314.0,
    "sellCount": 182.0,
    "sellQuantity": 566486.0,
    "adjRatio": 1.0,
    "currentForeignRoom": 0.0,
    "propTradingNetDealValue": 0.0,
    "propTradingNetPTValue": 0.0,
    "propTradingNetValue": 0.0,
    "unit": 1000.0
  },
  {
    "date": "2025-04-09T00:00:00",
    "symbol": "ACC",
    "priceHigh": 14.4,
    "priceLow": 13.45,
    "priceOpen": 13.5,
    "priceAverage": 13.66253604036521,
    "priceClose": 14.3,
    "priceBasic": 14.45,
    "totalVolume": 832400.0,
    "dealVolume": 832400.0,
    "putthroughVolume": 0.0,
    "totalValue": 11372695000.0,
    "putthroughValue": 0.0,
    "buyForeignQuantity": 0.0,
    "buyForeignValue": 0.0,
    "sellForeignQuantity": 0.0,
    "sellForeignValue": 0.0,
    "buyCount": 113.0,
    "buyQuantity": 871822.0,
    "sellCount": 167.0,
    "sellQuantity": 1153642.0,
    "adjRatio": 1.0,
    "currentForeignRoom": 0.0,
    "propTradingNetDealValue": 0.0,
    "propTradingNetPTValue": 0.0,
    "propTradingNetValue": 0.0,
    "unit": 1000.0
  },
  {
    "date": "2025-04-08T00:00:00",
    "symbol": "ACC",
    "priceHigh": 14.55,
    "priceLow": 13.65,
    "priceOpen": 14.55,
    "priceAverage": 13.879924042620528,
    "priceClose": 14.45,
    "priceBasic": 14.65,
    "totalVolume": 947900.0,
    "dealVolume": 947900.0,
    "putthroughVolume": 0.0,
    "totalValue": 13156780000.0,
    "putthroughValue": 0.0,
    "buyForeignQuantity": 0.0,
    "buyForeignValue": 0.0,
    "sellForeignQuantity": 0.0,
    "sellForeignValue": 0.0,
    "buyCount": 92.0,
    "buyQuantity": 957113.0,
    "sellCount": 180.0,
    "sellQuantity": 1249758.0,
    "adjRatio": 1.0,
    "currentForeignRoom": 0.0,
    "propTradingNetDealValue": 0.0,
    "propTradingNetPTValue": 0.0,
    "propTradingNetValue": 0.0,
    "unit": 1000.0
  },
  {
    "date": "2025-04-04T00:00:00",
    "symbol": "ACC",
    "priceHigh": 14.65,
    "priceLow": 13.65,
    "priceOpen": 13.65,
    "priceAverage": 14.272625400213446,
    "priceClose": 14.65,
    "priceBasic": 14.65,
    "totalVolume": 93700.0,
    "dealVolume": 93700.0,
    "putthroughVolume": 0.0,
    "totalValue": 1337345000.0,
    "putthroughValue": 0.0,
    "buyForeignQuantity": 0.0,
    "buyForeignValue": 0.0,
    "sellForeignQuantity": 0.0,
    "sellForeignValue": 0.0,
    "buyCount": 74.0,
    "buyQuantity": 250791.0,
    "sellCount": 75.0,
    "sellQuantity": 455699.0,
    "adjRatio": 1.0,
    "currentForeignRoom": 0.0,
    "propTradingNetDealValue": 0.0,
    "propTradingNetPTValue": 0.0,
    "propTradingNetValue": 0.0,
    "unit": 1000.0
  },
  {
    "date": "2025-04-03T00:00:00",
    "symbol": "ACC",
    "priceHigh": 14.65,
    "priceLow": 13.65,
    "priceOpen": 14.15,
    "priceAverage": 14.10351966873706,
    "priceClose": 14.65,
    "priceBasic": 14.65,
    "totalVolume": 96600.0,
    "dealVolume": 96600.0,
    "putthroughVolume": 0.0,
    "totalValue": 1362400000.0,
    "putthroughValue": 0.0,
    "buyForeignQuantity": 0.0,
    "buyForeignValue": 0.0,
    "sellForeignQuantity": 0.0,
    "sellForeignValue": 0.0,
    "buyCount": 78.0,
    "buyQuantity": 134272.0,
    "sellCount": 97.0,
    "sellQuantity": 270059.0,
    "adjRatio": 1.0,
    "currentForeignRoom": 0.0,
    "propTradingNetDealValue": 0.0,
    "propTradingNetPTValue": 0.0,
    "propTradingNetValue": 0.0,
    "unit": 1000.0
  },
  {
    "date": "2025-04-02T00:00:00",
    "symbol": "ACC",
    "priceHigh": 14.7,
    "priceLow": 14.5,
    "priceOpen": 14.7,
    "priceAverage": 14.648558322411533,
    "priceClose": 14.65,
    "priceBasic": 14.65,
    "totalVolume": 76300.0,
    "dealVolume": 76300.0,
    "putthroughVolume": 0.0,
    "totalValue": 1117685000.0,
    "putthroughValue": 0.0,
    "buyForeignQuantity": 0.0,
    "buyForeignValue": 0.0,
    "sellForeignQuantity": 0.0,
    "sellForeignValue": 0.0,
    "buyCount": 51.0,
    "buyQuantity": 136119.0,
    "sellCount": 81.0,
    "sellQuantity": 216175.0,
    "adjRatio": 1.0,
    "currentForeignRoom": 0.0,
    "propTradingNetDealValue": 0.0,
    "propTradingNetPTValue": 0.0,
    "propTradingNetValue": 0.0,
    "unit": 1000.0
  },
  {
    "date": "2025-04-01T00:00:00",
    "symbol": "ACC",
    "priceHigh": 14.65,
    "priceLow": 14.45,
    "priceOpen": 14.5,
    "priceAverage": 14.50679347826087,
    "priceClose": 14.65,
    "priceBasic": 14.7,
    "totalVolume": 18400.0,
    "dealVolume": 18400.0,
    "putthroughVolume": 0.0,
    "totalValue": 266925000.0,
    "putthroughValue": 0.0,
    "buyForeignQuantity": 0.0,
    "buyForeignValue": 0.0,
    "sellForeignQuantity": 0.0,
    "sellForeignValue": 0.0,
    "buyCount": 49.0,
    "buyQuantity": 62406.0,
    "sellCount": 57.0,
    "sellQuantity": 185608.0,
    "adjRatio": 1.0,
    "currentForeignRoom": 0.0,
    "propTradingNetDealValue": 0.0,
    "propTradingNetPTValue": 0.0,
    "propTradingNetValue": 0.0,
    "unit": 1000.0
  }
]