[
  {
    "date": "2024-12-31T00:00:00",
    "symbol": "PNJ",
    "priceHigh": 97.9,
    "priceLow": 97.5,
    "priceOpen": 97.5,
    "priceAverage": 97.78711631663974,
    "priceClose": 97.9,
    "priceBasic": 97.5,
    "totalVolume": 495201.0,
    "dealVolume": 495200.0,
    "putthroughVolume": 1.0,
    "totalValue": 48424270700.0,
    "putthroughValue": 90700.0,
    "buyForeignQuantity": 900.0,
    "buyForeignValue": 87750000.0,
    "sellForeignQuantity": 1400.0,
    "sellForeignValue": 136920000.0,
    "buyCount": 461.0,
    "buyQuantity": 742429.0,
    "sellCount": 982.0,
    "sellQuantity": 1304238.0,
    "adjRatio": 1.0061412487,
    "currentForeignRoom": 0.0,
    "propTradingNetDealValue": -4912540000.0,
    "propTradingNetPTValue": -91000.0,
    "propTradingNetValue": -4912631000.0,
    "unit": 1000.0
  },
  {
    "date": "2024-12-30T00:00:00",
    "symbol": "PNJ",
    "priceHigh": 98.5,
    "priceLow": 97.2,
    "priceOpen": 97.5,
    "priceAverage": 97.95889357479534,
    "priceClose": 97.5,
    "priceBasic": 97.6,
    "totalVolume": 1161212.0,
    "dealVolume": 806200.0,
    "putthroughVolume": 355012.0,
    "totalValue": 113588049600.0,
    "putthroughValue": 34613589600.0,
    "buyForeignQuantity": 0.0,
    "buyForeignValue": 0.0,
    "sellForeignQuantity": 0.0,
    "sellForeignValue": 0.0,
    "buyCount": 926.0,
    "buyQuantity": 1375517.0,
    "sellCount": 1421.0,
    "sellQuantity": 1999975.0,
    "adjRatio": 1.0061412487,
    "currentForeignRoom": 0.0,
    "propTradingNetDealValue": -1602530000.0,
    "propTradingNetPTValue": -1090000.0,
    "propTradingNetValue": -1603620000.0,
    "unit": 1000.0
  },
  {
    "date": "2024-12-27T00:00:00",
    "symbol": "PNJ",
    "priceHigh": 97.6,
    "priceLow": 97.0,
    "priceOpen": 97.6,
    "priceAverage": 97.42928951184147,
    "priceClose": 97.6,
    "priceBasic": 97.5,
    "totalVolume": 693804.0,
    "dealVolume": 413800.0,
    "putthroughVolume": 280004.0,
    "totalValue": 67616602800.0,
    "putthroughValue": 27300362800.0,
    "buyForeignQuantity": 10000.0,
    "buyForeignValue": 976000000.0,
    "sellForeignQuantity": 0.0,
    "sellForeignValue": 0.0,
    "buyCount": 517.0,
    "buyQuantity": 782662.0,
    "sellCount": 754.0,
    "sellQuantity": 1065093.0,
    "adjRatio": 1.0061412487,
    "currentForeignRoom": 0.0,
    "propTradingNetDealValue": -1997840000.0,
    "propTradingNetPTValue": -363000.0,
    "propTradingNetValue": -1998203000.0,
    "unit": 1000.0
  },
  {
    "date": "2024-12-26T00:00:00",
    "symbol": "PNJ",
    "priceHigh": 98.0,
    "priceLow": 97.1,
    "priceOpen": 97.9,
    "priceAverage": 97.58401639344262,
    "priceClose": 97.5,
    "priceBasic": 97.6,
    "totalVolume": 414803.0,
    "dealVolume": 414800.0,
    "putthroughVolume": 3.0,
    "totalValue": 40478122400.0,
    "putthroughValue": 272400.0,
    "buyForeignQuantity": 11200.0,
    "buyForeignValue": 1096480000.0,
    "sellForeignQuantity": 900.0,
    "sellForeignValue": 87750000.0,
    "buyCount": 685.0,
    "buyQuantity": 793877.0,
    "sellCount": 1046.0,
    "sellQuantity": 1435100.0,
    "adjRatio": 1.0061412487,
    "currentForeignRoom": 0.0,
    "propTradingNetDealValue": 679680000.0,
    "propTradingNetPTValue": -272000.0,
    "propTradingNetValue": 679408000.0,
    "unit": 1000.0
  },
  {
    "date": "2024-12-25T00:00:00",
    "symbol": "PNJ",
    "priceHigh": 97.9,
    "priceLow": 97.0,
    "priceOpen": 97.5,
    "priceAverage": 97.43282608695652,
    "priceClose": 97.6,
    "priceBasic": 97.2,
    "totalVolume": 506004.0,
    "dealVolume": 506000.0,
    "putthroughVolume": 4.0,
    "totalValue": 49301371600.0,
    "putthroughValue": 361600.0,
    "buyForeignQuantity": 0.0,
    "buyForeignValue": 0.0,
    "sellForeignQuantity": 0.0,
    "sellForeignValue": 0.0,
    "buyCount": 608.0,
    "buyQuantity": 995968.0,
    "sellCount": 1034.0,
    "sellQuantity": 1318386.0,
    "adjRatio": 1.0061412487,
    "currentForeignRoom": 0.0,
    "propTradingNetDealValue": 4589250000.0,
    "propTradingNetPTValue": -362000.0,
    "propTradingNetValue": 4588888000.0,
    "unit": 1000.0
  },
  {
    "date": "2024-12-24T00:00:00",
    "symbol": "PNJ",
    "priceHigh": 97.3,
    "priceLow": 96.0,
    "priceOpen": 97.3,
    "priceAverage": 96.70485933503836,
    "priceClose": 97.2,
    "priceBasic": 97.3,
    "totalVolume": 508304.0,
    "dealVolume": 508300.0,
    "putthroughVolume": 4.0,
    "totalValue": 49155442000.0,
    "putthroughValue": 362000.0,
    "buyForeignQuantity": 11900.0,
    "buyForeignValue": 1157870000.0,
    "sellForeignQuantity": 10000.0,
    "sellForeignValue": 966050000.0,
    "buyCount": 858.0,
    "buyQuantity": 1016278.0,
    "sellCount": 849.0,
    "sellQuantity": 1360886.0,
    "adjRatio": 1.0061412487,
    "currentForeignRoom": 0.0,
    "propTradingNetDealValue": 4288380000.0,
    "propTradingNetPTValue": -362000.0,
    "propTradingNetValue": 4288018000.0,
    "unit": 1000.0
  },
  {
    "date": "2024-12-23T00:00:00",
    "symbol": "PNJ",
    "priceHigh": 97.8,
    "priceLow": 96.9,
    "priceOpen": 97.0,
    "priceAverage": 97.20668410345829,
    "priceClose": 97.3,
    "priceBasic": 97.0,
    "totalVolume": 344109.0,
    "dealVolume": 344100.0,
    "putthroughVolume": 9.0,
    "totalValue": 33449632700.0,
    "putthroughValue": 812700.0,
    "buyForeignQuantity": 0.0,
    "buyForeignValue": 0.0,
    "sellForeignQuantity": 11200.0,
    "sellForeignValue": 1090000000.0,
    "buyCount": 413.0,
    "buyQuantity": 652836.0,
    "sellCount": 804.0,
    "sellQuantity": 1014103.0,
    "adjRatio": 1.0061412487,
    "currentForeignRoom": 0.0,
    "propTradingNetDealValue": -389200000.0,
    "propTradingNetPTValue": -813000.0,
    "propTradingNetValue": -390013000.0,
    "unit": 1000.0
  },
  {
    "date": "2024-12-20T00:00:00",
    "symbol": "PNJ",
    "priceHigh": 97.4,
    "priceLow": 96.8,
    "priceOpen": 97.2,
    "priceAverage": 96.95973451327434,
    "priceClose": 97.0,
    "priceBasic": 97.4,
    "totalVolume": 405390.0,
    "dealVolume": 180800.0,
    "putthroughVolume": 224590.0,
    "totalValue": 39457404300.0,
    "putthroughValue": 21927084300.0,
    "buyForeignQuantity": 34002.0,
    "buyForeignValue": 3344910000.0,
    "sellForeignQuantity": 34000.0,
    "sellForeignValue": 3344720000.0,
    "buyCount": 520.0,
    "buyQuantity": 513636.0,
    "sellCount": 611.0,
    "sellQuantity": 706786.0,
    "adjRatio": 1.0061412487,
    "currentForeignRoom": 0.0,
    "propTradingNetDealValue": 0.0,
    "propTradingNetPTValue": -272000.0,
    "propTradingNetValue": -272000.0,
    "unit": 1000.0
  },
  {
    "date": "2024-12-19T00:00:00",
    "symbol": "PNJ",
    "priceHigh": 97.4,
    "priceLow": 96.4,
    "priceOpen": 96.6,
    "priceAverage": 96.9264549384769,
    "priceClose": 97.4,
    "priceBasic": 97.5,
    "totalVolume": 1139736.0,
    "dealVolume": 601400.0,
    "putthroughVolume": 538336.0,
    "totalValue": 110859380380.0,
    "putthroughValue": 52567810380.0,
    "buyForeignQuantity": 66234.0,
    "buyForeignValue": 6534580000.0,
    "sellForeignQuantity": 74234.0,
    "sellForeignValue": 7311310000.0,
    "buyCount": 709.0,
    "buyQuantity": 1207584.0,
    "sellCount": 856.0,
    "sellQuantity": 1180246.0,
    "adjRatio": 1.0061412487,
    "currentForeignRoom": 0.0,
    "propTradingNetDealValue": -8702700000.0,
    "propTradingNetPTValue": 0.0,
    "propTradingNetValue": -8702700000.0,
    "unit": 1000.0
  },
  {
    "date": "2024-12-18T00:00:00",
    "symbol": "PNJ",
    "priceHigh": 97.8,
    "priceLow": 97.0,
    "priceOpen": 97.6,
    "priceAverage": 97.2899310758166,
    "priceClose": 97.5,
    "priceBasic": 97.8,
    "totalVolume": 333707.0,
    "dealVolume": 333700.0,
    "putthroughVolume": 7.0,
    "totalValue": 32466287000.0,
    "putthroughValue": 637000.0,
    "buyForeignQuantity": 0.0,
    "buyForeignValue": 0.0,
    "sellForeignQuantity": 4000.0,
    "sellForeignValue": 388940000.0,
    "buyCount": 639.0,
    "buyQuantity": 699148.0,
    "sellCount": 812.0,
    "sellQuantity": 850717.0,
    "adjRatio": 1.0061412487,
    "currentForeignRoom": 0.0,
    "propTradingNetDealValue": 2800220000.0,
    "propTradingNetPTValue": -637000.0,
    "propTradingNetValue": 2799583000.0,
    "unit": 1000.0
  },
  {
    "date": "2024-12-17T00:00:00",
    "symbol": "PNJ",
    "priceHigh": 98.1,
    "priceLow": 97.5,
    "priceOpen": 98.0,
    "priceAverage": 97.75851792186872,
    "priceClose": 97.8,
    "priceBasic": 98.2,
    "totalVolume": 303404.0,
    "dealVolume": 248300.0,
    "putthroughVolume": 55104.0,
    "totalValue": 29537370600.0,
    "putthroughValue": 5263930600.0,
    "buyForeignQuantity": 27500.0,
    "buyForeignValue": 2741010000.0,
    "sellForeignQuantity": 2.0,
    "sellForeignValue": 200000.0,
    "buyCount": 598.0,
    "buyQuantity": 799050.0,
    "sellCount": 817.0,
    "sellQuantity": 1045832.0,
    "adjRatio": 1.0061412487,
    "currentForeignRoom": 0.0,
    "propTradingNetDealValue": 2399870000.0,
    "propTradingNetPTValue": -2741374000.0,
    "propTradingNetValue": -341504000.0,
    "unit": 1000.0
  },
  {
    "date": "2024-12-16T00:00:00",
    "symbol": "PNJ",
    "priceHigh": 99.1,
    "priceLow": 97.5,
    "priceOpen": 97.5,
    "priceAverage": 98.48175840233804,
    "priceClose": 98.2,
    "priceBasic": 97.0,
    "totalVolume": 1357808.0,
    "dealVolume": 1231800.0,
    "putthroughVolume": 126008.0,
    "totalValue": 133856092400.0,
    "putthroughValue": 12546262400.0,
    "buyForeignQuantity": 126200.0,
    "buyForeignValue": 12565480000.0,
    "sellForeignQuantity": 129900.0,
    "sellForeignValue": 12931210000.0,
    "buyCount": 1040.0,
    "buyQuantity": 2439826.0,
    "sellCount": 2646.0,
    "sellQuantity": 2992822.0,
    "adjRatio": 1.0061412487,
    "currentForeignRoom": 0.0,
    "propTradingNetDealValue": -10439120000.0,
    "propTradingNetPTValue": -722000.0,
    "propTradingNetValue": -10439842000.0,
    "unit": 1000.0
  },
  {
    "date": "2024-12-13T00:00:00",
    "symbol": "PNJ",
    "priceHigh": 97.1,
    "priceLow": 96.6,
    "priceOpen": 97.0,
    "priceAverage": 96.8301038598667,
    "priceClose": 97.0,
    "priceBasic": 96.8,
    "totalVolume": 690606.0,
    "dealVolume": 645100.0,
    "putthroughVolume": 45506.0,
    "totalValue": 66913720600.0,
    "putthroughValue": 4448620600.0,
    "buyForeignQuantity": 45500.0,
    "buyForeignValue": 4448440000.0,
    "sellForeignQuantity": 45500.0,
    "sellForeignValue": 4448440000.0,
    "buyCount": 509.0,
    "buyQuantity": 1020209.0,
    "sellCount": 947.0,
    "sellQuantity": 1682212.0,
    "adjRatio": 1.0061412487,
    "currentForeignRoom": 0.0,
    "propTradingNetDealValue": -3270610000.0,
    "propTradingNetPTValue": -541000.0,
    "propTradingNetValue": -3271151000.0,
    "unit": 1000.0
  },
  {
    "date": "2024-12-12T00:00:00",
    "symbol": "PNJ",
    "priceHigh": 98.1,
    "priceLow": 96.2,
    "priceOpen": 96.8,
    "priceAverage": 97.31574963201795,
    "priceClose": 96.8,
    "priceBasic": 96.8,
    "totalVolume": 2083705.0,
    "dealVolume": 1426700.0,
    "putthroughVolume": 657005.0,
    "totalValue": 203410790500.0,
    "putthroughValue": 64570410500.0,
    "buyForeignQuantity": 657000.0,
    "buyForeignValue": 64575870000.0,
    "sellForeignQuantity": 684500.0,
    "sellForeignValue": 67262850000.0,
    "buyCount": 817.0,
    "buyQuantity": 2201531.0,
    "sellCount": 1729.0,
    "sellQuantity": 2829853.0,
    "adjRatio": 1.0061412487,
    "currentForeignRoom": 0.0,
    "propTradingNetDealValue": -22085730000.0,
    "propTradingNetPTValue": -451000.0,
    "propTradingNetValue": -22086181000.0,
    "unit": 1000.0
  },
  {
    "date": "2024-12-11T00:00:00",
    "symbol": "PNJ",
    "priceHigh": 97.0,
    "priceLow": 96.2,
    "priceOpen": 96.7,
    "priceAverage": 96.5511288056206,
    "priceClose": 96.8,
    "priceBasic": 97.0,
    "totalVolume": 1067509.0,
    "dealVolume": 1067500.0,
    "putthroughVolume": 9.0,
    "totalValue": 103069142700.0,
    "putthroughValue": 812700.0,
    "buyForeignQuantity": 100.0,
    "buyForeignValue": 9670000.0,
    "sellForeignQuantity": 200.0,
    "sellForeignValue": 19330000.0,
    "buyCount": 588.0,
    "buyQuantity": 1483299.0,
    "sellCount": 1106.0,
    "sellQuantity": 1991776.0,
    "adjRatio": 1.0061412487,
    "currentForeignRoom": 0.0,
    "propTradingNetDealValue": 86340000.0,
    "propTradingNetPTValue": -813000.0,
    "propTradingNetValue": 85527000.0,
    "unit": 1000.0
  },
  {
    "date": "2024-12-10T00:00:00",
    "symbol": "PNJ",
    "priceHigh": 97.6,
    "priceLow": 96.3,
    "priceOpen": 97.0,
    "priceAverage": 96.98137241658786,
    "priceClose": 97.0,
    "priceBasic": 96.8,
    "totalVolume": 740302.0,
    "dealVolume": 740300.0,
    "putthroughVolume": 2.0,
    "totalValue": 71795490200.0,
    "putthroughValue": 180200.0,
    "buyForeignQuantity": 47021.0,
    "buyForeignValue": 4570620000.0,
    "sellForeignQuantity": 0.0,
    "sellForeignValue": 0.0,
    "buyCount": 705.0,
    "buyQuantity": 1111849.0,
    "sellCount": 1588.0,
    "sellQuantity": 2047693.0,
    "adjRatio": 1.0061412487,
    "currentForeignRoom": 0.0,
    "propTradingNetDealValue": 1007100000.0,
    "propTradingNetPTValue": -180000.0,
    "propTradingNetValue": 1006920000.0,
    "unit": 1000.0
  },
  {
    "date": "2024-12-09T00:00:00",
    "symbol": "PNJ",
    "priceHigh": 97.4,
    "priceLow": 96.6,
    "priceOpen": 96.7,
    "priceAverage": 96.9968896139206,
    "priceClose": 96.8,
    "priceBasic": 96.4,
    "totalVolume": 919506.0,
    "dealVolume": 919500.0,
    "putthroughVolume": 6.0,
    "totalValue": 89189178200.0,
    "putthroughValue": 538200.0,
    "buyForeignQuantity": 33600.0,
    "buyForeignValue": 3259270000.0,
    "sellForeignQuantity": 0.0,
    "sellForeignValue": 0.0,
    "buyCount": 725.0,
    "buyQuantity": 1490290.0,
    "sellCount": 1805.0,
    "sellQuantity": 2180944.0,
    "adjRatio": 1.0061412487,
    "currentForeignRoom": 0.0,
    "propTradingNetDealValue": 652800000.0,
    "propTradingNetPTValue": -538000.0,
    "propTradingNetValue": 652262000.0,
    "unit": 1000.0
  },
  {
    "date": "2024-12-06T00:00:00",
    "symbol": "PNJ",
    "priceHigh": 96.5,
    "priceLow": 95.7,
    "priceOpen": 96.4,
    "priceAverage": 96.15024141260864,
    "priceClose": 96.4,
    "priceBasic": 96.0,
    "totalVolume": 724900.0,
    "dealVolume": 724900.0,
    "putthroughVolume": 0.0,
    "totalValue": 69699310000.0,
    "putthroughValue": 0.0,
    "buyForeignQuantity": 71201.0,
    "buyForeignValue": 6846830000.0,
    "sellForeignQuantity": 100.0,
    "sellForeignValue": 9570000.0,
    "buyCount": 688.0,
    "buyQuantity": 1104076.0,
    "sellCount": 1548.0,
    "sellQuantity": 1603774.0,
    "adjRatio": 1.0061412487,
    "currentForeignRoom": 0.0,
    "propTradingNetDealValue": -1297780000.0,
    "propTradingNetPTValue": 0.0,
    "propTradingNetValue": -1297780000.0,
    "unit": 1000.0
  },
  {
    "date": "2024-12-05T00:00:00",
    "symbol": "PNJ",
    "priceHigh": 96.7,
    "priceLow": 94.4,
    "priceOpen": 94.4,
    "priceAverage": 95.58034010464758,
    "priceClose": 96.0,
    "priceBasic": 94.2,
    "totalVolume": 1299600.0,
    "dealVolume": 1299600.0,
    "putthroughVolume": 0.0,
    "totalValue": 124216210000.0,
    "putthroughValue": 0.0,
    "buyForeignQuantity": 14900.0,
    "buyForeignValue": 1423900000.0,
    "sellForeignQuantity": 47021.0,
    "sellForeignValue": 4484010000.0,
    "buyCount": 1216.0,
    "buyQuantity": 2515358.0,
    "sellCount": 2808.0,
    "sellQuantity": 2530165.0,
    "adjRatio": 1.0061412487,
    "currentForeignRoom": 71201.0,
    "propTradingNetDealValue": -1377460000.0,
    "propTradingNetPTValue": 0.0,
    "propTradingNetValue": -1377460000.0,
    "unit": 1000.0
  },
  {
    "date": "2024-12-04T00:00:00",
    "symbol": "PNJ",
    "priceHigh": 94.3,
    "priceLow": 93.5,
    "priceOpen": 93.7,
    "priceAverage": 93.81296041571146,
    "priceClose": 94.2,
    "priceBasic": 93.6,
    "totalVolume": 684300.0,
    "dealVolume": 654300.0,
    "putthroughVolume": 30000.0,
    "totalValue": 64192220000.0,
    "putthroughValue": 2810400000.0,
    "buyForeignQuantity": 280.0,
    "buyForeignValue": 26230000.0,
    "sellForeignQuantity": 33600.0,
    "sellForeignValue": 3147870000.0,
    "buyCount": 993.0,
    "buyQuantity": 1293980.0,
    "sellCount": 939.0,
    "sellQuantity": 1106585.0,
    "adjRatio": 1.0061412487,
    "currentForeignRoom": 1.0,
    "propTradingNetDealValue": -5678070000.0,
    "propTradingNetPTValue": -2810550000.0,
    "propTradingNetValue": -8488620000.0,
    "unit": 1000.0
  },
  {
    "date": "2024-12-03T00:00:00",
    "symbol": "PNJ",
    "priceHigh": 94.2,
    "priceLow": 93.6,
    "priceOpen": 94.0,
    "priceAverage": 93.8987597346409,
    "priceClose": 93.6,
    "priceBasic": 94.0,
    "totalVolume": 346700.0,
    "dealVolume": 346700.0,
    "putthroughVolume": 0.0,
    "totalValue": 32554700000.0,
    "putthroughValue": 0.0,
    "buyForeignQuantity": 15800.0,
    "buyForeignValue": 1484860000.0,
    "sellForeignQuantity": 0.0,
    "sellForeignValue": 0.0,
    "buyCount": 496.0,
    "buyQuantity": 788755.0,
    "sellCount": 817.0,
    "sellQuantity": 855521.0,
    "adjRatio": 1.0061412487,
    "currentForeignRoom": 23.0,
    "propTradingNetDealValue": -10029860000.0,
    "propTradingNetPTValue": 0.0,
    "propTradingNetValue": -10029860000.0,
    "unit": 1000.0
  },
  {
    "date": "2024-12-02T00:00:00",
    "symbol": "PNJ",
    "priceHigh": 94.3,
    "priceLow": 93.0,
    "priceOpen": 93.0,
    "priceAverage": 93.70469283987663,
    "priceClose": 94.0,
    "priceBasic": 92.9,
    "totalVolume": 1626100.0,
    "dealVolume": 1199700.0,
    "putthroughVolume": 426400.0,
    "totalValue": 152222200000.0,
    "putthroughValue": 39804680000.0,
    "buyForeignQuantity": 861555.0,
    "buyForeignValue": 80500450000.0,
    "sellForeignQuantity": 302500.0,
    "sellForeignValue": 28330170000.0,
    "buyCount": 1170.0,
    "buyQuantity": 2040949.0,
    "sellCount": 1554.0,
    "sellQuantity": 1895376.0,
    "adjRatio": 1.0061412487,
    "currentForeignRoom": 15823.0,
    "propTradingNetDealValue": -9370270000.0,
    "propTradingNetPTValue": -17670000000.0,
    "propTradingNetValue": -27040270000.0,
    "unit": 1000.0
  }
]